[
  {
    "address": "5GsPUZ4evDtgCzugn8N4EKC79r9xaXUoZpkDKxoL4u83u8p2",
    "totalStake": "84384553391426495743685",
    "ownStake": "72816830677142127794980",
    "otherStake": "11567722714284367948705",
    "nominatorCount": 623,
    "commission": 1,
    "expectedReturn": 580.6874407527995,
    "blocked": false,
    "isVerified": false,
    "minBond": "0",
    "isCrowded": true,
    "eraRewardPoint": "175160",
    "topQuartile": true
  },
  {
    "address": "5FHVuL3oV82Phxytsru1kjPk5aXmNTKuuPMk3jLuCh8KmvGh",
    "totalStake": "84384017546864196011445",
    "ownStake": "74970060630058043498225",
    "otherStake": "9413956916806152513220",
    "nominatorCount": 313,
    "commission": 1,
    "expectedReturn": 580.6874407527995,
    "blocked": false,
    "isVerified": false,
    "minBond": "0",
    "isCrowded": true,
    "eraRewardPoint": "169400",
    "topQuartile": false
  },
  {
    "address": "5GecVbjDdEL4Q1TNztpewVwG8crfchFJtnbphQYrUApv5PYV",
    "totalStake": "84384172199578072663230",
    "ownStake": "73895605115840103018365",
    "otherStake": "10488567083737969644865",
    "nominatorCount": 189,
    "commission": 1,
    "expectedReturn": 580.6874407527995,
    "blocked": false,
    "isVerified": false,
    "minBond": "0",
    "isCrowded": false,
    "eraRewardPoint": "175560",
    "topQuartile": true
  },
  {
    "address": "5FPE7yUQzQ7SkKN2R4LUp85cz8HjUAqWHvxtLxQgGnKhXWP5",
    "totalStake": "84384059217606942364630",
    "ownStake": "74103814429911368865900",
    "otherStake": "10280244787695573498730",
    "nominatorCount": 162,
    "commission": 1,
    "expectedReturn": 580.6874407527995,
    "blocked": false,
    "isVerified": false,
    "minBond": "0",
    "isCrowded": false,
    "eraRewardPoint": "168640",
    "topQuartile": false
  },
  {
    "address": "5GKaoJf8nA9TX9JhzchyBujsTZEHhV69n5ZHr79wqyRP69Qa",
    "totalStake": "84383957834016332326085",
    "ownStake": "71450565162119484886925",
    "otherStake": "12933392671896847439160",
    "nominatorCount": 48,
    "commission": 1,
    "expectedReturn": 580.6874407527995,
    "blocked": false,
    "isVerified": false,
    "minBond": "0",
    "isCrowded": false,
    "eraRewardPoint": "176660",
    "topQuartile": true
  },
  {
    "address": "5GsgTh96pRwnixVjJ1qPRKb5Y18qHej36jVFR1HNdvA7B9sy",
    "totalStake": "84384024791324481756140",
    "ownStake": "77290980486364827397925",
    "otherStake": "7093044304959654358215",
    "nominatorCount": 93,
    "commission": 1,
    "expectedReturn": 580.6874407527995,
    "blocked": false,
    "isVerified": false,
    "minBond": "0",
    "isCrowded": false,
    "eraRewardPoint": "167520",
    "topQuartile": false
  },
  {
    "address": "5EpmLpPmd8tMCeMjVEMsd4YqbFjhXEixEcAGQWBSVr4J6iY8",
    "totalStake": "84383925692143105324385",
    "ownStake": "73164060997434434943600",
    "otherStake": "11219864694708670380785",
    "nominatorCount": 72,
    "commission": 1,
    "expectedReturn": 580.6874407527995,
    "blocked": false,
    "isVerified": false,
    "minBond": "0",
    "isCrowded": false,
    "eraRewardPoint": "170240",
    "topQuartile": true
  }
]