[
  {
    "commission": 10,
    "address": "dfcK5HkVwKXeeAUusJgpvHYM8hoJB2GUYQTmHqLLsGWcuo49i",
    "totalStake": "1077405461794986099884556",
    "ownStake": "400000000000000000000000",
    "otherStake": "677405461794986099884556",
    "nominatorCount": 107,
    "blocked": false,
    "isVerified": false,
    "minBond": "752540000000000000000",
    "chain": "manta_network",
    "isCrowded": true,
    "expectedReturn": 32.04041993578669
  },
  {
    "commission": 10,
    "address": "dfX4wjkSgdGYJQNZPUAa5A3y78xNx59LqkTZebgHW8j4tT8Wi",
    "totalStake": "942018620000000000000000",
    "ownStake": "400000000000000000000000",
    "otherStake": "542018620000000000000000",
    "nominatorCount": 102,
    "blocked": false,
    "isVerified": false,
    "minBond": "823000000000000000000",
    "chain": "manta_network",
    "isCrowded": true,
    "expectedReturn": 35.46079714993931
  },
  {
    "commission": 10,
    "address": "dfbmUJG9739gqaxXrLwuGaVjSEcUTkvSYwwyBibrhL2HqXWnh",
    "totalStake": "1042259577512448282843298",
    "ownStake": "400000000000000000000000",
    "otherStake": "642259577512448282843298",
    "nominatorCount": 98,
    "blocked": false,
    "isVerified": false,
    "minBond": "902210000000000000000",
    "chain": "manta_network",
    "isCrowded": true,
    "expectedReturn": 33.12033223360841
  },
  {
    "commission": 10,
    "address": "dfZgjh3DZBxYf5WcH2fFkU97i5AjHzNCASLDqcajBs4MitzAu",
    "totalStake": "1000816730000000000000000",
    "ownStake": "400000000000000000000000",
    "otherStake": "600816730000000000000000",
    "nominatorCount": 102,
    "blocked": false,
    "isVerified": false,
    "minBond": "551880000000000000000",
    "chain": "manta_network",
    "isCrowded": true,
    "expectedReturn": 34.491128143828604
  },
  {
    "commission": 10,
    "address": "dfYKSiyGWBGKhQ6sbT1563wVeqLaHZ9cv6UHyYhL8iv1WC6MC",
    "totalStake": "962711919969883722292484",
    "ownStake": "400000000000000000000000",
    "otherStake": "562711919969883722292484",
    "nominatorCount": 95,
    "blocked": false,
    "isVerified": false,
    "minBond": "502980000000000000000",
    "chain": "manta_network",
    "isCrowded": true,
    "expectedReturn": 35.85560241828119
  },
  {
    "commission": 10,
    "address": "dfZ6CNvSDW6rbZJYc6RVCpYJA7AD7fxrERMsF7EzCjNqqVg5W",
    "totalStake": "766977648421898510970313",
    "ownStake": "400000000000000000000000",
    "otherStake": "366977648421898510970313",
    "nominatorCount": 110,
    "blocked": false,
    "isVerified": false,
    "minBond": "775000000000000000000",
    "chain": "manta_network",
    "isCrowded": true,
    "expectedReturn": 45.0000644553025
  },
  {
    "commission": 10,
    "address": "dfbK9hvN2tHBceugrxkCavAF8VVXBLaqLfnEVWYeU1c1hjPnL",
    "totalStake": "842711311666659886241323",
    "ownStake": "400000000000000000000000",
    "otherStake": "442711311666659886241323",
    "nominatorCount": 138,
    "blocked": false,
    "isVerified": false,
    "minBond": "606000000000000000000",
    "chain": "manta_network",
    "isCrowded": true,
    "expectedReturn": 42.27958663131834
  },
  {
    "commission": 10,
    "address": "dfYNfURPkwF8nW42F6GhmfoGYgqNTwbPxk3tEQvnxGrYtKQj1",
    "totalStake": "1012139900000000000000000",
    "ownStake": "400000000000000000000000",
    "otherStake": "612139900000000000000000",
    "nominatorCount": 102,
    "blocked": false,
    "isVerified": false,
    "minBond": "903270000000000000000",
    "chain": "manta_network",
    "isCrowded": true,
    "expectedReturn": 30.804926299668175
  },
  {
    "commission": 10,
    "address": "dfYCDPFoLhU9GjAu5L7qXqM3WJ6UHvkgsBRVj3PLR56cQDi1k",
    "totalStake": "887246030000000000000000",
    "ownStake": "400000000000000000000000",
    "otherStake": "487246030000000000000000",
    "nominatorCount": 102,
    "blocked": false,
    "isVerified": false,
    "minBond": "1002510000000000000000",
    "chain": "manta_network",
    "isCrowded": true,
    "expectedReturn": 38.90363063295189
  },
  {
    "commission": 10,
    "address": "dfbXhEizE4KCq9uQ9ajBU6HJxv2gaD4JrGnE58spWPdaskuDA",
    "totalStake": "1113166247834027746031508",
    "ownStake": "400000000000000000000000",
    "otherStake": "713166247834027746031508",
    "nominatorCount": 102,
    "blocked": false,
    "isVerified": false,
    "minBond": "750000000000000000000",
    "chain": "manta_network",
    "isCrowded": true,
    "expectedReturn": 31.011574351076575
  },
  {
    "commission": 10,
    "address": "dfXsebvgud3qDeadPf6747xiC7fp1ZDQwMnfL6soMgX6b1Q3q",
    "totalStake": "848216107729457761039271",
    "ownStake": "400000000000000000000000",
    "otherStake": "448216107729457761039271",
    "nominatorCount": 101,
    "blocked": false,
    "isVerified": false,
    "minBond": "802520000000000000000",
    "chain": "manta_network",
    "isCrowded": true,
    "expectedReturn": 40.69269256522526
  },
  {
    "commission": 10,
    "address": "dfXjk5o6SH7xZ6hzz1CX2oBFzLMcCyfSzHoLPwQ2aCGxEcXef",
    "totalStake": "972913340000000000000000",
    "ownStake": "400000000000000000000000",
    "otherStake": "572913340000000000000000",
    "nominatorCount": 102,
    "blocked": false,
    "isVerified": false,
    "minBond": "690000000000000000000",
    "chain": "manta_network",
    "isCrowded": true,
    "expectedReturn": 35.479833928503
  },
  {
    "commission": 10,
    "address": "dfabGCMsPPryBnXEkJK64wx5VDRFb1YM5DXxEyinZHrQ1qbHB",
    "totalStake": "810220883395280914198752",
    "ownStake": "400000000000000000000000",
    "otherStake": "410220883395280914198752",
    "nominatorCount": 123,
    "blocked": false,
    "isVerified": false,
    "minBond": "919700000000000000000",
    "chain": "manta_network",
    "isCrowded": true,
    "expectedReturn": 41.22560831773349
  },
  {
    "commission": 10,
    "address": "dfafqAJkRGRy4B5kSttFyysPYz4V1jCgcuvqgdYk2sWN9sCjF",
    "totalStake": "985863447590019506225184",
    "ownStake": "400000000000000000000000",
    "otherStake": "585863447590019506225184",
    "nominatorCount": 103,
    "blocked": false,
    "isVerified": false,
    "minBond": "690000000000000000000",
    "chain": "manta_network",
    "isCrowded": true,
    "expectedReturn": 35.014014085145305
  },
  {
    "commission": 10,
    "address": "dfbXk7oF7jWXavGuryTyjKxKdojqokhWVU7LS13S1Rt8JY5aN",
    "totalStake": "957983647163507428707104",
    "ownStake": "400000000000000000000000",
    "otherStake": "557983647163507428707104",
    "nominatorCount": 102,
    "blocked": false,
    "isVerified": false,
    "minBond": "748850000000000000000",
    "chain": "manta_network",
    "isCrowded": true,
    "expectedReturn": 31.38312846911126
  },
  {
    "commission": 10,
    "address": "dfYgeCPabdxHMqP8rhvD6QEEpvQfXAUBurx9DcrpnuuY6rxRq",
    "totalStake": "787472250000000000000000",
    "ownStake": "400000000000000000000000",
    "otherStake": "387472250000000000000000",
    "nominatorCount": 113,
    "blocked": false,
    "isVerified": false,
    "minBond": "965000000000000000000",
    "chain": "manta_network",
    "isCrowded": true,
    "expectedReturn": 42.415785065858266
  },
  {
    "commission": 10,
    "address": "dfaNNpjHpjJunKrCz12DgLDVoi15fQtNio7yLBUpAV9jPf8bz",
    "totalStake": "768521117849841315389165",
    "ownStake": "400000000000000000000000",
    "otherStake": "368521117849841315389165",
    "nominatorCount": 110,
    "blocked": false,
    "isVerified": false,
    "minBond": "1008000000000000000000",
    "chain": "manta_network",
    "isCrowded": true,
    "expectedReturn": 44.90974674863612
  },
  {
    "commission": 10,
    "address": "dfbubzPdnd6WdWJFmX8pGEgYKY9EzUbxzMjNrsDFG36tisSoy",
    "totalStake": "770576912268985698968290",
    "ownStake": "400000000000000000000000",
    "otherStake": "370576912268985698968290",
    "nominatorCount": 123,
    "blocked": false,
    "isVerified": false,
    "minBond": "1004650000000000000000",
    "chain": "manta_network",
    "isCrowded": true,
    "expectedReturn": 44.79001134317656
  },
  {
    "commission": 10,
    "address": "dfarLxJpqVtH38Q1V4i2EnLmiikgQmpGTnzMQ7yDXZvPFbWio",
    "totalStake": "806377306685390887626609",
    "ownStake": "400000000000000000000000",
    "otherStake": "406377306685390887626609",
    "nominatorCount": 106,
    "blocked": false,
    "isVerified": false,
    "minBond": "1030570000000000000000",
    "chain": "manta_network",
    "isCrowded": true,
    "expectedReturn": 13.807329118044985
  },
  {
    "commission": 10,
    "address": "dfXKj9kmF2utL2x8fxQoWMaKGXumXW3GS64CoMaJzuAW1KsEx",
    "totalStake": "919137610000000000000000",
    "ownStake": "400000000000000000000000",
    "otherStake": "519137610000000000000000",
    "nominatorCount": 101,
    "blocked": false,
    "isVerified": false,
    "minBond": "560000000000000000000",
    "chain": "manta_network",
    "isCrowded": true,
    "expectedReturn": 37.55451416019123
  },
  {
    "commission": 10,
    "address": "dfZmrwiRJ2Qziad6FaYzvLdSW6u3ZNqZcU7FURSzNfJK3UTAe",
    "totalStake": "790305050000000000000000",
    "ownStake": "400000000000000000000000",
    "otherStake": "390305050000000000000000",
    "nominatorCount": 107,
    "blocked": false,
    "isVerified": false,
    "minBond": "727000000000000000000",
    "chain": "manta_network",
    "isCrowded": true,
    "expectedReturn": 43.67263922630416
  },
  {
    "commission": 10,
    "address": "dfX4pQUnjMPgBWtsKEab9L2NAVMAVtmVsUTyHj3egs5EuV9m9",
    "totalStake": "1031650030000000000000000",
    "ownStake": "400000000000000000000000",
    "otherStake": "631650030000000000000000",
    "nominatorCount": 110,
    "blocked": false,
    "isVerified": false,
    "minBond": "966000000000000000000",
    "chain": "manta_network",
    "isCrowded": true,
    "expectedReturn": 32.38139865563995
  },
  {
    "commission": 10,
    "address": "dfbM24qYytnWYmzso4tmx1sd5S7teFGGSJuthbL93CeEzfTFX",
    "totalStake": "1003642890000000000000000",
    "ownStake": "400001000000000000000000",
    "otherStake": "603641890000000000000000",
    "nominatorCount": 103,
    "blocked": false,
    "isVerified": false,
    "minBond": "680000000000000000000",
    "chain": "manta_network",
    "isCrowded": true,
    "expectedReturn": 35.5035384457267
  },
  {
    "commission": 10,
    "address": "dfaWMYxRAX2EMwUvCtf4Xk53U4vSgedTDmzjMeYxg6ULTAKKZ",
    "totalStake": "811410662994936011307509",
    "ownStake": "400000000000000000000000",
    "otherStake": "411410662994936011307509",
    "nominatorCount": 117,
    "blocked": false,
    "isVerified": false,
    "minBond": "1009790000000000000000",
    "chain": "manta_network",
    "isCrowded": true,
    "expectedReturn": 41.165196021165194
  },
  {
    "commission": 10,
    "address": "dfZh4fiDbcGqXQoi5o3fHzeFJvAkJUoBCKv4qazAV3JYfLfNQ",
    "totalStake": "502037460000000000000000",
    "ownStake": "400000000000000000000000",
    "otherStake": "102037460000000000000000",
    "nominatorCount": 51,
    "blocked": false,
    "isVerified": false,
    "minBond": "502170000000000000000",
    "chain": "manta_network",
    "isCrowded": true,
    "expectedReturn": 62.07357654015156
  },
  {
    "commission": 10,
    "address": "dfXBuufwGHyWF2ggdYVE5xcNXuAt9vNNWUnJzoe9kCoc9A3ve",
    "totalStake": "798781653514425479030853",
    "ownStake": "400000000000000000000000",
    "otherStake": "398781653514425479030853",
    "nominatorCount": 103,
    "blocked": false,
    "isVerified": false,
    "minBond": "566940000000000000000",
    "chain": "manta_network",
    "isCrowded": true,
    "expectedReturn": 43.20947878026842
  },
  {
    "commission": 10,
    "address": "dfbXrLky69zMg9PKaJNtVGThhk32f9jEYCZTSaDfmxWExeZad",
    "totalStake": "1239627080000000000000000",
    "ownStake": "400100000000000000000000",
    "otherStake": "839527080000000000000000",
    "nominatorCount": 108,
    "blocked": false,
    "isVerified": false,
    "minBond": "1150000000000000000000",
    "chain": "manta_network",
    "isCrowded": true,
    "expectedReturn": 25.154113631325068
  },
  {
    "commission": 10,
    "address": "dfXJ6FcEjmG3DGBXrVGzPjbLpQv6y51dg8ANqNfa23tzqGfmu",
    "totalStake": "795462610000000000000000",
    "ownStake": "400000000000000000000000",
    "otherStake": "395462610000000000000000",
    "nominatorCount": 129,
    "blocked": false,
    "isVerified": false,
    "minBond": "936000000000000000000",
    "chain": "manta_network",
    "isCrowded": true,
    "expectedReturn": 43.38965576158084
  },
  {
    "commission": 10,
    "address": "dfZYPuCevYRLyH3nPSNcZJb8LPuYaSby16PgWA2eE64kUvV6A",
    "totalStake": "591532103531504150925922",
    "ownStake": "400000000000000000000000",
    "otherStake": "191532103531504150925922",
    "nominatorCount": 71,
    "blocked": false,
    "isVerified": false,
    "minBond": "500000000000000000000",
    "chain": "manta_network",
    "isCrowded": true,
    "expectedReturn": 16.93613981125039
  },
  {
    "commission": 10,
    "address": "dfbpEqMgg2vFsuh9hL9afwvRCXs3LWiVSMbDQ6kVZ8SMUQtR7",
    "totalStake": "837101870000000000000000",
    "ownStake": "400000000000000000000000",
    "otherStake": "437101870000000000000000",
    "nominatorCount": 119,
    "blocked": false,
    "isVerified": false,
    "minBond": "1240440000000000000000",
    "chain": "manta_network",
    "isCrowded": true,
    "expectedReturn": 38.57247780587219
  },
  {
    "commission": 10,
    "address": "dfYq23dCFus7HPomFYUtzqqKSYkywobsvesYwKwJYpMctvhYg",
    "totalStake": "899689970000000000000000",
    "ownStake": "400000000000000000000000",
    "otherStake": "499689970000000000000000",
    "nominatorCount": 101,
    "blocked": false,
    "isVerified": false,
    "minBond": "897000000000000000000",
    "chain": "manta_network",
    "isCrowded": true,
    "expectedReturn": 35.89062377659245
  },
  {
    "commission": 10,
    "address": "dfc5ADDU2sBkCWoNGDngj8FQiysWGvczPjwTH7YiTywSZeRFd",
    "totalStake": "845206100000000000000000",
    "ownStake": "400000000000000000000000",
    "otherStake": "445206100000000000000000",
    "nominatorCount": 117,
    "blocked": false,
    "isVerified": false,
    "minBond": "1005930000000000000000",
    "chain": "manta_network",
    "isCrowded": true,
    "expectedReturn": 40.83752458092643
  },
  {
    "commission": 10,
    "address": "dfXe5ucmRDLSHoTHjm6YvxFvmda5L3vsccJLf9LwLNCv4dV5V",
    "totalStake": "801118171672377013631899",
    "ownStake": "400000000000000000000000",
    "otherStake": "401118171672377013631899",
    "nominatorCount": 124,
    "blocked": false,
    "isVerified": false,
    "minBond": "1039530000000000000000",
    "chain": "manta_network",
    "isCrowded": true,
    "expectedReturn": 43.0835338661766
  },
  {
    "commission": 10,
    "address": "dfaJiUPDTXRzkEJynHRztvBFKN2CUQ7zWEahC738civiL3nj7",
    "totalStake": "790340621143044103918968",
    "ownStake": "400000000000000000000000",
    "otherStake": "390340621143044103918968",
    "nominatorCount": 121,
    "blocked": false,
    "isVerified": false,
    "minBond": "1000000000000000000000",
    "chain": "manta_network",
    "isCrowded": true,
    "expectedReturn": 40.85321198351574
  },
  {
    "commission": 10,
    "address": "dfc3EvNJJri5S22rBua9pWfWnuBG6NdBaxSgfpJXM9t6jaTq6",
    "totalStake": "956327990000000000000000",
    "ownStake": "400000000000000000000000",
    "otherStake": "556327990000000000000000",
    "nominatorCount": 103,
    "blocked": false,
    "isVerified": false,
    "minBond": "850000000000000000000",
    "chain": "manta_network",
    "isCrowded": true,
    "expectedReturn": 36.09483000909017
  },
  {
    "commission": 10,
    "address": "dfabcqYPTnKTamQEuuRytZyx7wHspxmLtqSn1gKRkSLVzM4hW",
    "totalStake": "956033060000000000000000",
    "ownStake": "400000000000000000000000",
    "otherStake": "556033060000000000000000",
    "nominatorCount": 100,
    "blocked": false,
    "isVerified": false,
    "minBond": "512400000000000000000",
    "chain": "manta_network",
    "isCrowded": true,
    "expectedReturn": 36.105959209595355
  },
  {
    "commission": 10,
    "address": "dfZduNW2BEgfzic1tFFqdxo6MZA2fXDg2gJNueJ1zJF1UGAfo",
    "totalStake": "827646937512461531162532",
    "ownStake": "400000000000000000000000",
    "otherStake": "427646937512461531162532",
    "nominatorCount": 119,
    "blocked": false,
    "isVerified": false,
    "minBond": "933000000000000000000",
    "chain": "manta_network",
    "isCrowded": true,
    "expectedReturn": 41.70340078866709
  },
  {
    "commission": 10,
    "address": "dfaVzsSbPgzgHWG75Mi29gdVDFdERr5HT5SN3Y1iovoGeoKKD",
    "totalStake": "1056461910000000000000000",
    "ownStake": "400001450000000000000000",
    "otherStake": "656460460000000000000000",
    "nominatorCount": 100,
    "blocked": false,
    "isVerified": false,
    "minBond": "529150000000000000000",
    "chain": "manta_network",
    "isCrowded": true,
    "expectedReturn": 32.67529635669598
  },
  {
    "commission": 10,
    "address": "dfbAyQxtNoRPJ7N6djvb1xHLjXjoTdx7Wd9yYXwGnXu5Lk2q3",
    "totalStake": "831150860779202529500426",
    "ownStake": "400000000000000000000000",
    "otherStake": "431150860779202529500426",
    "nominatorCount": 101,
    "blocked": false,
    "isVerified": false,
    "minBond": "998620000000000000000",
    "chain": "manta_network",
    "isCrowded": true,
    "expectedReturn": 41.52769542573543
  },
  {
    "commission": 10,
    "address": "dfbmYdZKX3kyKJP46G8uhEcv9h6AidBxJRv6V2v7B7RBNTkPf",
    "totalStake": "786942130000000000000000",
    "ownStake": "400000000000000000000000",
    "otherStake": "386942130000000000000000",
    "nominatorCount": 104,
    "blocked": false,
    "isVerified": false,
    "minBond": "762000000000000000000",
    "chain": "manta_network",
    "isCrowded": true,
    "expectedReturn": 42.4443401242206
  },
  {
    "commission": 10,
    "address": "dfY4DoQohsfUTaoh8H8wAhqKHRc86F1njrTeAna535ALGZMpP",
    "totalStake": "1005251772203431453574080",
    "ownStake": "400000000000000000000000",
    "otherStake": "605251772203431453574080",
    "nominatorCount": 100,
    "blocked": false,
    "isVerified": false,
    "minBond": "501000000000000000000",
    "chain": "manta_network",
    "isCrowded": true,
    "expectedReturn": 34.3390333494772
  },
  {
    "commission": 10,
    "address": "dfX4eP8BVjCfELzgiPuPWdq31PB83eVSUmHikAL1h4XzM2B2J",
    "totalStake": "830921260965000010610608",
    "ownStake": "400000000000000000000000",
    "otherStake": "430921260965000010610608",
    "nominatorCount": 118,
    "blocked": false,
    "isVerified": false,
    "minBond": "1008000000000000000000",
    "chain": "manta_network",
    "isCrowded": true,
    "expectedReturn": 38.85921741192052
  },
  {
    "commission": 10,
    "address": "dfZjiGTwgXDbpYkSdXvi9ykUjTWxmgTt8herCdyq2K2PuYRqR",
    "totalStake": "775359570000000000000000",
    "ownStake": "400000000000000000000000",
    "otherStake": "375359570000000000000000",
    "nominatorCount": 118,
    "blocked": false,
    "isVerified": false,
    "minBond": "1048000000000000000000",
    "chain": "manta_network",
    "isCrowded": true,
    "expectedReturn": 41.6420455324564
  },
  {
    "commission": 10,
    "address": "dfZGoguA6CiCwJATgZkp5MHuXTvrpc5vn3t5aX8d6qn8zsvW4",
    "totalStake": "982920811552036071673885",
    "ownStake": "400000000000000000000000",
    "otherStake": "582920811552036071673885",
    "nominatorCount": 102,
    "blocked": false,
    "isVerified": false,
    "minBond": "826310000000000000000",
    "chain": "manta_network",
    "isCrowded": true,
    "expectedReturn": 35.11878459485091
  },
  {
    "commission": 10,
    "address": "dfZDsaTYocdcnd9CusuNNqDM79gXQqdbKV5THp2aSyWGu6aHh",
    "totalStake": "1019800011000000000000000",
    "ownStake": "400000000000000000000000",
    "otherStake": "619800011000000000000000",
    "nominatorCount": 100,
    "blocked": false,
    "isVerified": false,
    "minBond": "500000000000000000000",
    "chain": "manta_network",
    "isCrowded": true,
    "expectedReturn": 31.66556815878741
  },
  {
    "commission": 10,
    "address": "dfbE3LfJAvdnNWBQmNv9bBUW3ieAjwijWZYRXx26uK3o2gTJZ",
    "totalStake": "951772550000000000000000",
    "ownStake": "400000000000000000000000",
    "otherStake": "551772550000000000000000",
    "nominatorCount": 100,
    "blocked": false,
    "isVerified": false,
    "minBond": "619560000000000000000",
    "chain": "manta_network",
    "isCrowded": true,
    "expectedReturn": 37.437418205657735
  },
  {
    "commission": 10,
    "address": "dfYpWcLbi3cRdsLiB4qtiCdHN2kN3fAFRHM3dxPU7zNHMmXWB",
    "totalStake": "498019550000000000000000",
    "ownStake": "400000000000000000000000",
    "otherStake": "98019550000000000000000",
    "nominatorCount": 61,
    "blocked": false,
    "isVerified": false,
    "minBond": "502000000000000000000",
    "chain": "manta_network",
    "isCrowded": true,
    "expectedReturn": 67.04343208578426
  },
  {
    "commission": 10,
    "address": "dfYRYnDZPFUkRgbymqSByLiRc3H4V3eJ9QLzydo19jz1jBDen",
    "totalStake": "806445840000000000000000",
    "ownStake": "400000000000000000000000",
    "otherStake": "406445840000000000000000",
    "nominatorCount": 119,
    "blocked": false,
    "isVerified": false,
    "minBond": "1162980000000000000000",
    "chain": "manta_network",
    "isCrowded": true,
    "expectedReturn": 41.418469415321276
  },
  {
    "commission": 10,
    "address": "dfZrje9EkTNELNtDVGSqpRkSUjcf8RqRmY7xmPxBZ6iubh8Hd",
    "totalStake": "794024680991488038158827",
    "ownStake": "400000000000000000000000",
    "otherStake": "394024680991488038158827",
    "nominatorCount": 106,
    "blocked": false,
    "isVerified": false,
    "minBond": "1114710000000000000000",
    "chain": "manta_network",
    "isCrowded": true,
    "expectedReturn": 43.46818226450969
  },
  {
    "commission": 10,
    "address": "dfYxprtVvL4aYB3bmUc22jNLbkqXmEFRwW67JkKsqSf65wGNG",
    "totalStake": "496327852098000000000000",
    "ownStake": "400000000000000000000000",
    "otherStake": "96327852098000000000000",
    "nominatorCount": 55,
    "blocked": false,
    "isVerified": false,
    "minBond": "500000000000000000000",
    "chain": "manta_network",
    "isCrowded": true,
    "expectedReturn": 69.51410534081137
  },
  {
    "commission": 10,
    "address": "dfc2ak1zSkgvNjXGVmaq6XQemkF5sZ4REs6s9NmoPv2SqV76t",
    "totalStake": "998604969646464807959277",
    "ownStake": "400000000000000000000000",
    "otherStake": "598604969646464807959277",
    "nominatorCount": 118,
    "blocked": false,
    "isVerified": false,
    "minBond": "783070000000000000000",
    "chain": "manta_network",
    "isCrowded": true,
    "expectedReturn": 30.107162258554876
  },
  {
    "commission": 10,
    "address": "dfZpHjEhq5v97FV6He8zBv7dSA2j6sc6sP5L6puWCga3Fn5Pn",
    "totalStake": "835507320000000000000000",
    "ownStake": "400000000000000000000000",
    "otherStake": "435507320000000000000000",
    "nominatorCount": 111,
    "blocked": false,
    "isVerified": false,
    "minBond": "1013750000000000000000",
    "chain": "manta_network",
    "isCrowded": true,
    "expectedReturn": 41.311293359236885
  },
  {
    "commission": 10,
    "address": "dfXX6A48doqMpFQLuysSa3Ke2vK7Z3Czuici43bjUT5pVC4uT",
    "totalStake": "824858330000000000000000",
    "ownStake": "400000000000000000000000",
    "otherStake": "424858330000000000000000",
    "nominatorCount": 108,
    "blocked": false,
    "isVerified": false,
    "minBond": "1014100000000000000000",
    "chain": "manta_network",
    "isCrowded": true,
    "expectedReturn": 41.84430251887011
  },
  {
    "commission": 10,
    "address": "dfXf2msgAqsESEfhxBAEDssoDtdzArFfDkJcKprb1AksLewWZ",
    "totalStake": "492973953531511626805922",
    "ownStake": "400000000000000000000000",
    "otherStake": "92973953531511626805922",
    "nominatorCount": 49,
    "blocked": false,
    "isVerified": false,
    "minBond": "500000000000000000000",
    "chain": "manta_network",
    "isCrowded": true,
    "expectedReturn": 69.9865583580067
  },
  {
    "commission": 10,
    "address": "dfZptUtPbsc6F5wieXo8ZYKAiXBaZ4weRTxYxQxTganFSTysP",
    "totalStake": "791660366858824305867165",
    "ownStake": "400000000000000000000000",
    "otherStake": "391660366858824305867165",
    "nominatorCount": 122,
    "blocked": false,
    "isVerified": false,
    "minBond": "524400000000000000000",
    "chain": "manta_network",
    "isCrowded": true,
    "expectedReturn": 40.78515019483412
  },
  {
    "commission": 10,
    "address": "dfXNJVYFc6uSzM6J8eeSn7zrpjnyZUNFQK4NLMxTFCSEsCkMs",
    "totalStake": "1012901018548589261398230",
    "ownStake": "400000000000000000000000",
    "otherStake": "612901018548589261398230",
    "nominatorCount": 87,
    "blocked": false,
    "isVerified": false,
    "minBond": "500000000000000000000",
    "chain": "manta_network",
    "isCrowded": true,
    "expectedReturn": 32.9804894430923
  },
  {
    "commission": 10,
    "address": "dfYHyS1NJVYxMYZDCF3p2TMkBt9CaaksUFjvLqSQtQrnKRqgC",
    "totalStake": "512053871263492217425430",
    "ownStake": "400000000000000000000000",
    "otherStake": "112053871263492217425430",
    "nominatorCount": 67,
    "blocked": false,
    "isVerified": false,
    "minBond": "500000000000000000000",
    "chain": "manta_network",
    "isCrowded": true,
    "expectedReturn": 65.20770492177009
  },
  {
    "commission": 10,
    "address": "dfbwiDius7bShBwKQ513NpSuJeXtNaZueErpAgsqbzME79x7f",
    "totalStake": "798831016000000000000000",
    "ownStake": "400000000000000000000000",
    "otherStake": "398831016000000000000000",
    "nominatorCount": 128,
    "blocked": false,
    "isVerified": false,
    "minBond": "1200000000000000000000",
    "chain": "manta_network",
    "isCrowded": true,
    "expectedReturn": 39.02550615851913
  },
  {
    "commission": 10,
    "address": "dfZGxB87kdmVijgTen8o7aCru4epW54yEXuJfDWfLjNSi8pEL",
    "totalStake": "1091007050000000000000000",
    "ownStake": "400001230000000000000000",
    "otherStake": "691005820000000000000000",
    "nominatorCount": 99,
    "blocked": false,
    "isVerified": false,
    "minBond": "803520000000000000000",
    "chain": "manta_network",
    "isCrowded": true,
    "expectedReturn": 31.641154903204175
  },
  {
    "commission": 10,
    "address": "dfYcFb8yaXMCqK4Cvs633q6VsAcX24BEVfVwqKpfBhgjYteiM",
    "totalStake": "921529382000000000000000",
    "ownStake": "400000000000000000000000",
    "otherStake": "521529382000000000000000",
    "nominatorCount": 99,
    "blocked": false,
    "isVerified": false,
    "minBond": "600000000000000000000",
    "chain": "manta_network",
    "isCrowded": true,
    "expectedReturn": 31.415629422258444
  },
  {
    "commission": 10,
    "address": "dfY9ANL1nKNtWuSMaviPgZ2oxHNPHCSqPhYjmACQNYY9HLcVQ",
    "totalStake": "792653546755572654495000",
    "ownStake": "400000000000000000000000",
    "otherStake": "392653546755572654495000",
    "nominatorCount": 132,
    "blocked": false,
    "isVerified": false,
    "minBond": "929200000000000000000",
    "chain": "manta_network",
    "isCrowded": true,
    "expectedReturn": 40.73407938839939
  }
]