[
  {
    "address": "5CFPcUJgYgWryPaV1aYjSbTpbTLu42V32Ytw1L9rfoMAsfGh",
    "totalStake": "94888832381832271",
    "ownStake": "20958371962165379",
    "otherStake": "73930460419666892",
    "nominatorCount": 0,
    "commission": 0,
    "expectedReturn": 19.44281573930119,
    "blocked": false,
    "isVerified": false,
    "minBond": "1000000000000",
    "isCrowded": false,
    "eraRewardPoint": "985940",
    "topQuartile": false
  },
  {
    "address": "5GTD7ZeD823BjpmZBCSzBQp7cvHR1Gunq7oDkurZr9zUev2n",
    "totalStake": "94898545045679527",
    "ownStake": "17250615299922584",
    "otherStake": "77647929745756943",
    "nominatorCount": 0,
    "commission": 1,
    "expectedReturn": 19.248387581908176,
    "blocked": false,
    "isVerified": false,
    "minBond": "1000000000000",
    "isCrowded": false,
    "eraRewardPoint": "1001980",
    "topQuartile": true
  },
  {
    "address": "5GYaYNVq6e855t5hVCyk4Wuqssaf6ADTrvdPZ3QXyHvFXTip",
    "totalStake": "94894604430217210",
    "ownStake": "30060867359578343",
    "otherStake": "64833737070638867",
    "nominatorCount": 0,
    "commission": 1,
    "expectedReturn": 19.248387581908176,
    "blocked": false,
    "isVerified": false,
    "minBond": "1000000000000",
    "isCrowded": false,
    "eraRewardPoint": "1001120",
    "topQuartile": true
  },
  {
    "address": "5CAsa5uG1i3Duq5NM1g8zYjNvUCwkwADxgFQiypSLTg6Hnwm",
    "totalStake": "94899639131907047",
    "ownStake": "137397965585635",
    "otherStake": "94762241166321412",
    "nominatorCount": 0,
    "commission": 1,
    "expectedReturn": 19.248387581908176,
    "blocked": false,
    "isVerified": false,
    "minBond": "1000000000000",
    "isCrowded": false,
    "eraRewardPoint": "30660",
    "topQuartile": false
  },
  {
    "address": "5CcHdjf6sPcEkTmXFzF2CfH7MFrVHyY5PZtSm1eZsxgsj1KC",
    "totalStake": "94889965594495117",
    "ownStake": "48082450355826519",
    "otherStake": "46807515238668598",
    "nominatorCount": 0,
    "commission": 1,
    "expectedReturn": 19.248387581908176,
    "blocked": false,
    "isVerified": false,
    "minBond": "1000000000000",
    "isCrowded": false,
    "eraRewardPoint": "850580",
    "topQuartile": false
  },
  {
    "address": "5G1ojzh47Yt8KoYhuAjXpHcazvsoCXe3G8LZchKDvumozJJJ",
    "totalStake": "94898287422079115",
    "ownStake": "31177054477082303",
    "otherStake": "63721232944996812",
    "nominatorCount": 0,
    "commission": 22,
    "expectedReturn": 15.165396276654926,
    "blocked": false,
    "isVerified": false,
    "minBond": "1000000000000",
    "isCrowded": false,
    "eraRewardPoint": "999740",
    "topQuartile": false
  },
  {
    "address": "5Ek5JCnrRsyUGYNRaEvkufG1i1EUxEE9cytuWBBjA9oNZVsf",
    "totalStake": "94894439006330657",
    "ownStake": "15093073953462448",
    "otherStake": "79801365052868209",
    "nominatorCount": 0,
    "commission": 1,
    "expectedReturn": 19.248387581908176,
    "blocked": false,
    "isVerified": false,
    "minBond": "1000000000000",
    "isCrowded": false,
    "eraRewardPoint": "1001180",
    "topQuartile": true
  },
  {
    "address": "5FZoQhgUCmqBxnkHX7jCqThScS2xQWiwiF61msg63CFL3Y8f",
    "totalStake": "94898808770959117",
    "ownStake": "22321551356442548",
    "otherStake": "72577257414516569",
    "nominatorCount": 0,
    "commission": 0,
    "expectedReturn": 19.44281573930119,
    "blocked": false,
    "isVerified": false,
    "minBond": "1000000000000",
    "isCrowded": false,
    "eraRewardPoint": "1002120",
    "topQuartile": true
  },
  {
    "address": "5ENXqYmc5m6VLMm5i1mun832xAv2Qm9t3M4PWAFvvyCJLNoR",
    "totalStake": "94892943733412218",
    "ownStake": "58875015879859588",
    "otherStake": "36017927853552630",
    "nominatorCount": 0,
    "commission": 1,
    "expectedReturn": 19.248387581908176,
    "blocked": false,
    "isVerified": false,
    "minBond": "1000000000000",
    "isCrowded": false,
    "eraRewardPoint": "1001420",
    "topQuartile": true
  },
  {
    "address": "5F1uUDXLgjLA4Ck9PssBWiSgqGQw24BgKLcjsjb8pRdDSx37",
    "totalStake": "94900099550033553",
    "ownStake": "5128754585836560",
    "otherStake": "89771344964196993",
    "nominatorCount": 0,
    "commission": 1,
    "expectedReturn": 19.248387581908176,
    "blocked": false,
    "isVerified": false,
    "minBond": "1000000000000",
    "isCrowded": false,
    "eraRewardPoint": "987720",
    "topQuartile": false
  },
  {
    "address": "5CFPqoTU7fiUp1JJNbfcY2z6yavEBKDPQGg4SGeG3Fm7vCsg",
    "totalStake": "94897133968158363",
    "ownStake": "30107920369223955",
    "otherStake": "64789213598934408",
    "nominatorCount": 0,
    "commission": 1,
    "expectedReturn": 19.248387581908176,
    "blocked": false,
    "isVerified": false,
    "minBond": "1000000000000",
    "isCrowded": false,
    "eraRewardPoint": "999260",
    "topQuartile": false
  },
  {
    "address": "5DJcEbkNxsnNwHGrseg7cgbfUG8eiKzpuZqgSph5HqHrjgf6",
    "totalStake": "94896195629427072",
    "ownStake": "48862752068041079",
    "otherStake": "46033443561385993",
    "nominatorCount": 0,
    "commission": 1,
    "expectedReturn": 19.248387581908176,
    "blocked": false,
    "isVerified": false,
    "minBond": "1000000000000",
    "isCrowded": false,
    "eraRewardPoint": "1003480",
    "topQuartile": true
  },
  {
    "address": "5HYYWyhyUQ7Ae11f8fCid58bhJ7ikLHM9bU8A6Ynwoc3dStR",
    "totalStake": "94894295318122734",
    "ownStake": "27024408923631722",
    "otherStake": "67869886394491012",
    "nominatorCount": 0,
    "commission": 12,
    "expectedReturn": 17.109677850585047,
    "blocked": false,
    "isVerified": false,
    "minBond": "1000000000000",
    "isCrowded": false,
    "eraRewardPoint": "1001320",
    "topQuartile": true
  },
  {
    "address": "5Ft3J6iqSQPWX2S9jERXcMpevt8JDUPWjec5uGierfVGXisE",
    "totalStake": "94997229515817145",
    "ownStake": "32776973610229890",
    "otherStake": "62220255905587255",
    "nominatorCount": 0,
    "commission": 1,
    "expectedReturn": 19.055903706089094,
    "blocked": false,
    "isVerified": false,
    "minBond": "1000000000000",
    "isCrowded": false,
    "eraRewardPoint": "1001080",
    "topQuartile": true
  },
  {
    "address": "5C556QTtg1bJ43GDSgeowa3Ark6aeSHGTac1b2rKSXtgmSmW",
    "totalStake": "94889257671532613",
    "ownStake": "32912286556727746",
    "otherStake": "61976971114804867",
    "nominatorCount": 0,
    "commission": 1,
    "expectedReturn": 19.248387581908176,
    "blocked": false,
    "isVerified": false,
    "minBond": "1000000000000",
    "isCrowded": false,
    "eraRewardPoint": "997740",
    "topQuartile": false
  },
  {
    "address": "5FEjMPSs4X2XNes7QRH6eLmaYCskHdnYM8Zv2kKrBrhnzGbR",
    "totalStake": "94887618912375946",
    "ownStake": "30186617748606837",
    "otherStake": "64701001163769109",
    "nominatorCount": 0,
    "commission": 1,
    "expectedReturn": 19.248387581908176,
    "blocked": false,
    "isVerified": false,
    "minBond": "1000000000000",
    "isCrowded": false,
    "eraRewardPoint": "1003040",
    "topQuartile": true
  },
  {
    "address": "5FUJHYEzKpVJfNbtXmR9HFqmcSEz6ak7ZUhBECz7GpsFkSYR",
    "totalStake": "94896773893113587",
    "ownStake": "32297938611129898",
    "otherStake": "62598835281983689",
    "nominatorCount": 0,
    "commission": 1,
    "expectedReturn": 19.248387581908176,
    "blocked": false,
    "isVerified": false,
    "minBond": "1000000000000",
    "isCrowded": false,
    "eraRewardPoint": "1000940",
    "topQuartile": false
  },
  {
    "address": "5E2CYS4D6KdD1nDh5d7hTtss3TR8etx4i92ozipJt5QtR9KY",
    "totalStake": "94889325344952185",
    "ownStake": "48921850446009464",
    "otherStake": "45967474898942721",
    "nominatorCount": 0,
    "commission": 1,
    "expectedReturn": 19.248387581908176,
    "blocked": false,
    "isVerified": false,
    "minBond": "1000000000000",
    "isCrowded": false,
    "eraRewardPoint": "999360",
    "topQuartile": false
  }
]