{
  "chainlink": {
    "cached_at": 1720221242123,
    "current_price": 12.33,
    "price_change_24h": -0.5680253677199953,
    "last_updated_at": "2024-07-05T23:13:53.957Z",
    "market_cap": 7488825253,
    "market_cap_rank": 17
  },
  "wrapped-astar": {
    "cached_at": 1720221242123,
    "current_price": 0.062162,
    "price_change_24h": -0.002686681191100063,
    "last_updated_at": "2024-07-05T23:13:17.696Z",
    "market_cap": 0,
    "market_cap_rank": null
  },
  "dot-is-ded": {
    "cached_at": 1720221242123,
    "current_price": 0.00018516,
    "price_change_24h": -0.000005497746992349,
    "last_updated_at": "2024-07-05T23:13:48.716Z",
    "market_cap": 0,
    "market_cap_rank": null
  },
  "tomochain": {
    "cached_at": 1720221242123,
    "current_price": 0.28344,
    "price_change_24h": -0.021661377820319298,
    "last_updated_at": "2024-07-05T23:13:42.057Z",
    "market_cap": 27860011,
    "market_cap_rank": 798
  },
  "ethereum": {
    "cached_at": 1720221242123,
    "current_price": 2983.8,
    "price_change_24h": -137.27942352648643,
    "last_updated_at": "2024-07-05T23:13:19.717Z",
    "market_cap": 358458087871,
    "market_cap_rank": 2
  },
  "rocket-pool-eth": {
    "cached_at": 1720221242123,
    "current_price": 3330.96,
    "price_change_24h": -157.65363898692385,
    "last_updated_at": "2024-07-05T23:13:37.531Z",
    "market_cap": 1671106785,
    "market_cap_rank": 51
  },
  "zenlink-network-token": {
    "cached_at": 1720221242123,
    "current_price": 0.01873384,
    "price_change_24h": -0.003044264333075628,
    "last_updated_at": "2024-07-05T23:13:46.780Z",
    "market_cap": 1018161,
    "market_cap_rank": 2682
  },
  "wrapped-stbtc": {
    "cached_at": 1720057442159,
    "current_price": 73992,
    "price_change_24h": -3108.2261676847847,
    "last_updated_at": "2024-07-04T01:35:25.116Z",
    "market_cap": 0,
    "market_cap_rank": null
  },
  "bifrost-native-coin": {
    "cached_at": 1720221242123,
    "current_price": 0.279115,
    "price_change_24h": -0.001771393913427011,
    "last_updated_at": "2024-07-05T23:13:37.896Z",
    "market_cap": 10662363,
    "market_cap_rank": 1251
  },
  "celo": {
    "cached_at": 1720221242123,
    "current_price": 0.471829,
    "price_change_24h": -0.028910069802398575,
    "last_updated_at": "2024-07-05T23:13:27.786Z",
    "market_cap": 255268486,
    "market_cap_rank": 201
  },
  "novatti-australian-digital-dollar": {
    "cached_at": 1720221242123,
    "current_price": 0.659521,
    "price_change_24h": 0.01441559,
    "last_updated_at": "2024-07-05T23:13:45.074Z",
    "market_cap": 0,
    "market_cap_rank": null
  },
  "wbnb": {
    "cached_at": 1720221242123,
    "current_price": 496.51,
    "price_change_24h": -28.039324498234862,
    "last_updated_at": "2024-07-05T23:13:25.604Z",
    "market_cap": 0,
    "market_cap_rank": null
  },
  "uncommon-goods": {
    "cached_at": 1720221242123,
    "current_price": 0.468232,
    "price_change_24h": -0.01850799297929412,
    "last_updated_at": "2024-07-05T23:12:27.573Z",
    "market_cap": 0,
    "market_cap_rank": null
  },
  "unique-network": {
    "cached_at": 1720221242123,
    "current_price": 0.00409798,
    "price_change_24h": 0.0000329,
    "last_updated_at": "2024-07-05T23:13:00.255Z",
    "market_cap": 1272955,
    "market_cap_rank": 2527
  },
  "lido-dao": {
    "cached_at": 1720221242123,
    "current_price": 1.59,
    "price_change_24h": -0.06683395265054992,
    "last_updated_at": "2024-07-05T23:13:40.222Z",
    "market_cap": 1418057313,
    "market_cap_rank": 61
  },
  "the-open-network": {
    "cached_at": 1720221242123,
    "current_price": 7.24,
    "price_change_24h": -0.0111887039140699,
    "last_updated_at": "2024-07-05T23:13:56.338Z",
    "market_cap": 18119860077,
    "market_cap_rank": 9
  },
  "nodle-network": {
    "cached_at": 1720221242123,
    "current_price": 0.00395388,
    "price_change_24h": 0.00015123,
    "last_updated_at": "2024-07-05T23:13:09.581Z",
    "market_cap": 14645954,
    "market_cap_rank": 1083
  },
  "kintsugi-btc": {
    "cached_at": 1720220702305,
    "current_price": 76455,
    "price_change_24h": 364.69,
    "last_updated_at": "2024-07-05T22:55:42.540Z",
    "market_cap": 0,
    "market_cap_rank": null
  },
  "kryptomon": {
    "cached_at": 1720221242123,
    "current_price": 0.00141116,
    "price_change_24h": -0.000093336264292252,
    "last_updated_at": "2024-07-05T23:13:46.391Z",
    "market_cap": 1185294,
    "market_cap_rank": 2572
  },
  "dogecoin": {
    "cached_at": 1720221242123,
    "current_price": 0.105355,
    "price_change_24h": -0.002095149013004089,
    "last_updated_at": "2024-07-05T23:13:23.346Z",
    "market_cap": 15226019984,
    "market_cap_rank": 10
  },
  "venus-busd": {
    "cached_at": 1720221242123,
    "current_price": 0.02199711,
    "price_change_24h": -0.000076255173836831,
    "last_updated_at": "2024-07-05T23:10:45.783Z",
    "market_cap": 0,
    "market_cap_rank": null
  },
  "binance-bitcoin": {
    "cached_at": 1720221242123,
    "current_price": 56671,
    "price_change_24h": -1526.9081514826248,
    "last_updated_at": "2024-07-05T23:13:31.825Z",
    "market_cap": 0,
    "market_cap_rank": null
  },
  "genshiro": {
    "cached_at": 1720221242123,
    "current_price": 0.00024713,
    "price_change_24h": -0.000016499703830727,
    "last_updated_at": "2024-07-05T23:13:47.506Z",
    "market_cap": 0,
    "market_cap_rank": null
  },
  "crypto-com-chain": {
    "cached_at": 1720221242123,
    "current_price": 0.084199,
    "price_change_24h": -0.001797393183495075,
    "last_updated_at": "2024-07-05T23:13:21.811Z",
    "market_cap": 2250531046,
    "market_cap_rank": 38
  },
  "voucher-dot": {
    "cached_at": 1720221242123,
    "current_price": 7.63,
    "price_change_24h": 0.057503,
    "last_updated_at": "2024-07-05T23:12:58.883Z",
    "market_cap": 0,
    "market_cap_rank": null
  },
  "ausd-seed-acala": {
    "cached_at": 1720220341941,
    "current_price": 0.457035,
    "price_change_24h": -0.020074395019955005,
    "last_updated_at": "2024-07-05T22:47:15.613Z",
    "market_cap": 0,
    "market_cap_rank": null
  },
  "binance-peg-polkadot": {
    "cached_at": 1720221242123,
    "current_price": 5.74,
    "price_change_24h": -0.006611693191548085,
    "last_updated_at": "2024-07-05T23:13:26.700Z",
    "market_cap": 0,
    "market_cap_rank": null
  },
  "interlay": {
    "cached_at": 1720221242123,
    "current_price": 0.0133523,
    "price_change_24h": -0.000128659233623115,
    "last_updated_at": "2024-07-05T23:13:13.830Z",
    "market_cap": 2037042,
    "market_cap_rank": 2215
  },
  "bido-staked-bitcoin": {
    "cached_at": 1719022622174,
    "current_price": null,
    "price_change_24h": null,
    "last_updated_at": null,
    "market_cap": null,
    "market_cap_rank": null
  },
  "humanode": {
    "cached_at": 1720221242123,
    "current_price": 0.121339,
    "price_change_24h": 0.00156041,
    "last_updated_at": "2024-07-05T23:13:39.062Z",
    "market_cap": 6343882,
    "market_cap_rank": 1540
  },
  "chiliz": {
    "cached_at": 1720221242123,
    "current_price": 0.06218,
    "price_change_24h": -0.002231034124469469,
    "last_updated_at": "2024-07-05T23:13:36.863Z",
    "market_cap": 551858439,
    "market_cap_rank": 118
  },
  "tether": {
    "cached_at": 1720221242123,
    "current_price": 1,
    "price_change_24h": -0.000016396906005856,
    "last_updated_at": "2024-07-05T23:10:50.052Z",
    "market_cap": 112327305152,
    "market_cap_rank": 3
  },
  "multibit": {
    "cached_at": 1720221242123,
    "current_price": 0.03148352,
    "price_change_24h": -0.002491160959106891,
    "last_updated_at": "2024-07-05T23:13:40.862Z",
    "market_cap": 29913165,
    "market_cap_rank": 771
  },
  "pups-ordinals": {
    "cached_at": 1720221242123,
    "current_price": 5.07,
    "price_change_24h": -0.7000493654079012,
    "last_updated_at": "2024-07-05T23:12:51.906Z",
    "market_cap": 39424474,
    "market_cap_rank": 647
  },
  "starlay-finance": {
    "cached_at": 1720220702305,
    "current_price": 0.0002091,
    "price_change_24h": -0.000002025462096465,
    "last_updated_at": "2024-07-05T22:52:27.853Z",
    "market_cap": 0,
    "market_cap_rank": null
  },
  "mythos": {
    "cached_at": 1720221242123,
    "current_price": 0.250812,
    "price_change_24h": -0.06442155621435236,
    "last_updated_at": "2024-07-05T23:13:42.547Z",
    "market_cap": 167484305,
    "market_cap_rank": 267
  },
  "uniswap": {
    "cached_at": 1720221242123,
    "current_price": 7.76,
    "price_change_24h": -0.052276602133125565,
    "last_updated_at": "2024-07-05T23:13:38.435Z",
    "market_cap": 5850759002,
    "market_cap_rank": 19
  },
  "axlusdc": {
    "cached_at": 1720221242123,
    "current_price": 1.001,
    "price_change_24h": 0.00375032,
    "last_updated_at": "2024-07-05T23:13:33.022Z",
    "market_cap": 0,
    "market_cap_rank": null
  },
  "astar": {
    "cached_at": 1720221242123,
    "current_price": 0.062084,
    "price_change_24h": -0.001570079612471888,
    "last_updated_at": "2024-07-05T23:13:57.479Z",
    "market_cap": 353481298,
    "market_cap_rank": 161
  },
  "usd": {
    "cached_at": 1720221242123,
    "current_price": 1.001,
    "price_change_24h": -0.000018950749250735,
    "last_updated_at": "2024-07-05T23:13:32.751Z",
    "market_cap": 63614266,
    "market_cap_rank": 501
  },
  "usd-coin": {
    "cached_at": 1720221242123,
    "current_price": 1.001,
    "price_change_24h": 0.00023486,
    "last_updated_at": "2024-07-05T23:13:20.939Z",
    "market_cap": 33613170522,
    "market_cap_rank": 6
  },
  "liquid-staking-dot": {
    "cached_at": 1720220341941,
    "current_price": 0.847376,
    "price_change_24h": 0.00734307,
    "last_updated_at": "2024-07-05T22:47:16.615Z",
    "market_cap": 0,
    "market_cap_rank": null
  },
  "shardeum": {
    "cached_at": 1717863902874,
    "current_price": null,
    "price_change_24h": null,
    "last_updated_at": null,
    "market_cap": null,
    "market_cap_rank": null
  },
  "quartz": {
    "cached_at": 1720221242123,
    "current_price": 0.00028322,
    "price_change_24h": -0.000003511845575118,
    "last_updated_at": "2024-07-05T23:13:11.893Z",
    "market_cap": 0,
    "market_cap_rank": null
  },
  "usdd": {
    "cached_at": 1720221242123,
    "current_price": 1.001,
    "price_change_24h": 0.00474015,
    "last_updated_at": "2024-07-05T23:13:51.432Z",
    "market_cap": 735985611,
    "market_cap_rank": 92
  },
  "voucher-glmr": {
    "cached_at": 1719962102642,
    "current_price": 0.252996,
    "price_change_24h": -0.003758930678957717,
    "last_updated_at": "2024-07-02T23:01:54.338Z",
    "market_cap": 0,
    "market_cap_rank": null
  },
  "sipher": {
    "cached_at": 1720221242123,
    "current_price": 0.181543,
    "price_change_24h": -0.027266762054845517,
    "last_updated_at": "2024-07-05T23:13:01.481Z",
    "market_cap": 17436894,
    "market_cap_rank": 1003
  },
  "civic": {
    "cached_at": 1720221242123,
    "current_price": 0.088888,
    "price_change_24h": -0.002501710624576742,
    "last_updated_at": "2024-07-05T23:13:25.820Z",
    "market_cap": 71182028,
    "market_cap_rank": 473
  },
  "rio-defi": {
    "cached_at": 1720221242123,
    "current_price": 0.00160184,
    "price_change_24h": -0.000099354304314472,
    "last_updated_at": "2024-07-05T23:13:30.236Z",
    "market_cap": 360155,
    "market_cap_rank": 3296
  },
  "soul-swap": {
    "cached_at": 1720220341941,
    "current_price": 0.00073203,
    "price_change_24h": -0.000053099027900907,
    "last_updated_at": "2024-07-05T22:43:41.257Z",
    "market_cap": 125579,
    "market_cap_rank": 3875
  },
  "bai-stablecoin": {
    "cached_at": 1720220341941,
    "current_price": 1,
    "price_change_24h": 0.0017543,
    "last_updated_at": "2024-07-05T22:47:17.678Z",
    "market_cap": 1255019,
    "market_cap_rank": 2538
  },
  "coin-capsule": {
    "cached_at": 1720221242123,
    "current_price": 0.00880906,
    "price_change_24h": -0.000281570874522649,
    "last_updated_at": "2024-07-05T23:13:53.163Z",
    "market_cap": 13774885,
    "market_cap_rank": 1107
  },
  "pendulum-chain": {
    "cached_at": 1720221242123,
    "current_price": 0.03885864,
    "price_change_24h": -0.002326278975252887,
    "last_updated_at": "2024-07-05T23:13:15.296Z",
    "market_cap": 1277215,
    "market_cap_rank": 2524
  },
  "epic-epic-epic-epic": {
    "cached_at": 1720221242123,
    "current_price": 0.039096,
    "price_change_24h": -0.002673613826119185,
    "last_updated_at": "2024-07-05T23:07:29.896Z",
    "market_cap": 0,
    "market_cap_rank": null
  },
  "ordinals": {
    "cached_at": 1720221242123,
    "current_price": 27.94,
    "price_change_24h": -3.5824439405580755,
    "last_updated_at": "2024-07-05T23:13:35.676Z",
    "market_cap": 586612248,
    "market_cap_rank": 109
  },
  "litentry": {
    "cached_at": 1720221242123,
    "current_price": 0.626835,
    "price_change_24h": -0.05539349333277798,
    "last_updated_at": "2024-07-05T23:13:31.730Z",
    "market_cap": 35509565,
    "market_cap_rank": 695
  },
  "polkadot": {
    "cached_at": 1720221242123,
    "current_price": 5.7,
    "price_change_24h": 0.0274853,
    "last_updated_at": "2024-07-05T23:13:56.045Z",
    "market_cap": 7890898604,
    "market_cap_rank": 16
  },
  "frax-share": {
    "cached_at": 1720221242123,
    "current_price": 2.43,
    "price_change_24h": -0.05663798183485147,
    "last_updated_at": "2024-07-05T23:13:36.544Z",
    "market_cap": 195039963,
    "market_cap_rank": 248
  },
  "fantom": {
    "cached_at": 1720221242123,
    "current_price": 0.427047,
    "price_change_24h": -0.026636182275506792,
    "last_updated_at": "2024-07-05T23:14:00.821Z",
    "market_cap": 1196471589,
    "market_cap_rank": 66
  },
  "crust-storage-market": {
    "cached_at": 1720221242123,
    "current_price": 0.0072857,
    "price_change_24h": 0.00072498,
    "last_updated_at": "2024-07-05T23:13:20.583Z",
    "market_cap": 0,
    "market_cap_rank": null
  },
  "shiden": {
    "cached_at": 1720221242123,
    "current_price": 0.154417,
    "price_change_24h": -0.006476416662657831,
    "last_updated_at": "2024-07-05T23:13:38.830Z",
    "market_cap": 10052751,
    "market_cap_rank": 1286
  },
  "claimswap": {
    "cached_at": 1720220341941,
    "current_price": 0.00090499,
    "price_change_24h": -0.000012254510303354,
    "last_updated_at": "2024-07-05T22:47:20.473Z",
    "market_cap": 0,
    "market_cap_rank": null
  },
  "metaverse-network-pioneer": {
    "cached_at": 1720221242123,
    "current_price": 0.04104224,
    "price_change_24h": -0.005054441741007977,
    "last_updated_at": "2024-07-05T23:13:40.530Z",
    "market_cap": 1550243,
    "market_cap_rank": 2408
  },
  "shiba-inu": {
    "cached_at": 1720221242123,
    "current_price": 0.00001483,
    "price_change_24h": -1.90390758305e-7,
    "last_updated_at": "2024-07-05T23:13:18.215Z",
    "market_cap": 8737554942,
    "market_cap_rank": 14
  },
  "xxcoin": {
    "cached_at": 1720221242123,
    "current_price": 0.081529,
    "price_change_24h": -0.003835611467476644,
    "last_updated_at": "2024-07-05T23:13:48.056Z",
    "market_cap": 0,
    "market_cap_rank": null
  },
  "ares-protocol": {
    "cached_at": 1720221242123,
    "current_price": 0.00048578,
    "price_change_24h": 0.00000511,
    "last_updated_at": "2024-07-05T23:13:04.467Z",
    "market_cap": 139433,
    "market_cap_rank": 3814
  },
  "creditcoin-2": {
    "cached_at": 1720221242123,
    "current_price": 0.454221,
    "price_change_24h": 0.01646523,
    "last_updated_at": "2024-07-05T23:13:36.877Z",
    "market_cap": 158596565,
    "market_cap_rank": 279
  },
  "xdai": {
    "cached_at": 1720221242123,
    "current_price": 1.003,
    "price_change_24h": 0.00506345,
    "last_updated_at": "2024-07-05T23:12:52.325Z",
    "market_cap": 0,
    "market_cap_rank": null
  },
  "binance-peg-xrp": {
    "cached_at": 1720221242123,
    "current_price": 0.424997,
    "price_change_24h": -0.019609827769895727,
    "last_updated_at": "2024-07-05T23:13:29.443Z",
    "market_cap": 0,
    "market_cap_rank": null
  },
  "okb": {
    "cached_at": 1720221242123,
    "current_price": 36.48,
    "price_change_24h": -3.8835364140750315,
    "last_updated_at": "2024-07-05T23:13:29.184Z",
    "market_cap": 2188592793,
    "market_cap_rank": 40
  },
  "dog-go-to-the-moon-rune": {
    "cached_at": 1720221242123,
    "current_price": 0.00480669,
    "price_change_24h": -0.000357768833946471,
    "last_updated_at": "2024-07-05T23:14:00.525Z",
    "market_cap": 479616740,
    "market_cap_rank": 135
  },
  "gala": {
    "cached_at": 1720221242123,
    "current_price": 0.02105427,
    "price_change_24h": -0.001998900082510424,
    "last_updated_at": "2024-07-05T23:13:56.880Z",
    "market_cap": 762340032,
    "market_cap_rank": 87
  },
  "coinmerge-os": {
    "cached_at": 1720221242123,
    "current_price": 0.0000632,
    "price_change_24h": -0.000001316615481286,
    "last_updated_at": "2024-07-05T23:09:38.434Z",
    "market_cap": 638012,
    "market_cap_rank": 2968
  },
  "deepbrain-chain": {
    "cached_at": 1720221242123,
    "current_price": 0.00277647,
    "price_change_24h": 0.00007997,
    "last_updated_at": "2024-07-05T23:13:22.958Z",
    "market_cap": 8901492,
    "market_cap_rank": 1360
  },
  "metis-token": {
    "cached_at": 1720221242123,
    "current_price": 35.99,
    "price_change_24h": -4.108744026053323,
    "last_updated_at": "2024-07-05T23:13:36.248Z",
    "market_cap": 204624490,
    "market_cap_rank": 237
  },
  "maker": {
    "cached_at": 1720221242123,
    "current_price": 2231.25,
    "price_change_24h": -35.63872436491329,
    "last_updated_at": "2024-07-05T23:14:00.997Z",
    "market_cap": 2074090939,
    "market_cap_rank": 42
  },
  "arthswap": {
    "cached_at": 1720221242123,
    "current_price": 0.00066427,
    "price_change_24h": -0.000139396736963155,
    "last_updated_at": "2024-07-05T23:13:52.697Z",
    "market_cap": 663831,
    "market_cap_rank": 2935
  },
  "curve-dao-token": {
    "cached_at": 1720221242123,
    "current_price": 0.236326,
    "price_change_24h": -0.012297330457947009,
    "last_updated_at": "2024-07-05T23:13:35.771Z",
    "market_cap": 288429597,
    "market_cap_rank": 179
  },
  "bouncebit": {
    "cached_at": 1720221242123,
    "current_price": 0.317789,
    "price_change_24h": -0.04706030338681816,
    "last_updated_at": "2024-07-05T23:13:24.447Z",
    "market_cap": 129795747,
    "market_cap_rank": 312
  },
  "tbtc": {
    "cached_at": 1720221242123,
    "current_price": 56353,
    "price_change_24h": -1561.522477911829,
    "last_updated_at": "2024-07-05T23:13:30.130Z",
    "market_cap": 181187390,
    "market_cap_rank": 259
  },
  "solarflare": {
    "cached_at": 1720221242123,
    "current_price": 0.00015181,
    "price_change_24h": -0.000008642186239957,
    "last_updated_at": "2024-07-05T23:07:30.376Z",
    "market_cap": 0,
    "market_cap_rank": null
  },
  "1inch": {
    "cached_at": 1720221242123,
    "current_price": 0.360379,
    "price_change_24h": 0.00567407,
    "last_updated_at": "2024-07-05T23:13:17.368Z",
    "market_cap": 450294521,
    "market_cap_rank": 140
  },
  "chainx": {
    "cached_at": 1720221242123,
    "current_price": 0.102055,
    "price_change_24h": 0.0035984,
    "last_updated_at": "2024-07-05T23:13:28.479Z",
    "market_cap": 0,
    "market_cap_rank": null
  },
  "manta-network": {
    "cached_at": 1720221242123,
    "current_price": 0.753556,
    "price_change_24h": -0.16379750670723403,
    "last_updated_at": "2024-07-05T23:13:41.676Z",
    "market_cap": 255505156,
    "market_cap_rank": 200
  },
  "astriddao-token": {
    "cached_at": 1717857182427,
    "current_price": 0.00010717,
    "price_change_24h": null,
    "last_updated_at": "2024-05-26T21:30:28.606Z",
    "market_cap": 42379,
    "market_cap_rank": 4262
  },
  "dent": {
    "cached_at": 1720221242123,
    "current_price": 0.00081612,
    "price_change_24h": -0.000069142357273213,
    "last_updated_at": "2024-07-05T23:13:33.570Z",
    "market_cap": 77875599,
    "market_cap_rank": 439
  },
  "avalanche-2": {
    "cached_at": 1720221242123,
    "current_price": 25.25,
    "price_change_24h": 0.377524,
    "last_updated_at": "2024-07-05T23:13:27.218Z",
    "market_cap": 9937377503,
    "market_cap_rank": 13
  },
  "jpyc": {
    "cached_at": 1720221242123,
    "current_price": 0.00681402,
    "price_change_24h": -0.000235422230566376,
    "last_updated_at": "2024-07-05T23:13:17.067Z",
    "market_cap": 0,
    "market_cap_rank": null
  },
  "near": {
    "cached_at": 1720221242123,
    "current_price": 4.43,
    "price_change_24h": -0.3309379443026925,
    "last_updated_at": "2024-07-05T23:13:26.786Z",
    "market_cap": 4848567373,
    "market_cap_rank": 22
  },
  "merlin-chain": {
    "cached_at": 1720221242123,
    "current_price": 0.213878,
    "price_change_24h": -0.024440673153044795,
    "last_updated_at": "2024-07-05T23:13:42.332Z",
    "market_cap": 77208190,
    "market_cap_rank": 443
  },
  "optimism": {
    "cached_at": 1720221242123,
    "current_price": 1.34,
    "price_change_24h": -0.157647549237397,
    "last_updated_at": "2024-07-05T23:13:56.041Z",
    "market_cap": 1498427252,
    "market_cap_rank": 55
  },
  "swapdex": {
    "cached_at": 1719797402353,
    "current_price": 0.00242934,
    "price_change_24h": null,
    "last_updated_at": "2023-08-01T20:44:09.073Z",
    "market_cap": 0,
    "market_cap_rank": null
  },
  "binancecoin": {
    "cached_at": 1720221242123,
    "current_price": 497.3,
    "price_change_24h": -25.482066858863448,
    "last_updated_at": "2024-07-05T23:13:58.650Z",
    "market_cap": 76451115803,
    "market_cap_rank": 4
  },
  "zeitgeist": {
    "cached_at": 1720221242123,
    "current_price": 0.03399118,
    "price_change_24h": -0.00175127389264626,
    "last_updated_at": "2024-07-05T23:13:54.336Z",
    "market_cap": 1573443,
    "market_cap_rank": 2396
  },
  "rats": {
    "cached_at": 1720221242123,
    "current_price": 0.00008721,
    "price_change_24h": -0.000019489931969452,
    "last_updated_at": "2024-07-05T23:13:20.557Z",
    "market_cap": 0,
    "market_cap_rank": null
  },
  "trac": {
    "cached_at": 1720221242123,
    "current_price": 1.53,
    "price_change_24h": -0.11766293408643103,
    "last_updated_at": "2024-07-05T23:13:23.678Z",
    "market_cap": 32105170,
    "market_cap_rank": 743
  },
  "basic-attention-token": {
    "cached_at": 1720221242123,
    "current_price": 0.168122,
    "price_change_24h": -0.005475486812352771,
    "last_updated_at": "2024-07-05T23:13:43.156Z",
    "market_cap": 250363035,
    "market_cap_rank": 204
  },
  "mangata-x": {
    "cached_at": 1720221242123,
    "current_price": 0.00035268,
    "price_change_24h": -0.000012555010540935,
    "last_updated_at": "2024-07-05T23:09:55.901Z",
    "market_cap": 0,
    "market_cap_rank": null
  },
  "moonriver": {
    "cached_at": 1720221242123,
    "current_price": 8.7,
    "price_change_24h": -0.9226899499078112,
    "last_updated_at": "2024-07-05T23:13:17.004Z",
    "market_cap": 78502415,
    "market_cap_rank": 437
  },
  "theta-token": {
    "cached_at": 1720221242123,
    "current_price": 1.28,
    "price_change_24h": -0.04622495688498218,
    "last_updated_at": "2024-07-05T23:13:31.558Z",
    "market_cap": 1278825158,
    "market_cap_rank": 64
  },
  "polimec": {
    "cached_at": 1720221242123,
    "current_price": 0.24981,
    "price_change_24h": 0.00268404,
    "last_updated_at": "2024-07-05T23:13:22.672Z",
    "market_cap": 13846093,
    "market_cap_rank": 1114
  },
  "sora": {
    "cached_at": 1720221242123,
    "current_price": 0.00001404,
    "price_change_24h": -5.37648997775e-7,
    "last_updated_at": "2024-07-05T23:13:58.984Z",
    "market_cap": 4289052,
    "market_cap_rank": 1765
  },
  "cncl": {
    "cached_at": 1719974402422,
    "current_price": 24.58,
    "price_change_24h": -0.33048332732987973,
    "last_updated_at": "2024-07-03T02:30:38.215Z",
    "market_cap": 246098,
    "market_cap_rank": 3574
  },
  "bouncebit-usd": {
    "cached_at": 1720221242123,
    "current_price": 0.982999,
    "price_change_24h": -0.007005213418769585,
    "last_updated_at": "2024-07-05T23:14:00.028Z",
    "market_cap": 0,
    "market_cap_rank": null
  },
  "kyber-network-crystal": {
    "cached_at": 1720221242123,
    "current_price": 0.448016,
    "price_change_24h": -0.032295367692916355,
    "last_updated_at": "2024-07-05T23:13:25.948Z",
    "market_cap": 76298933,
    "market_cap_rank": 450
  },
  "cypress": {
    "cached_at": 1720221242123,
    "current_price": 0.0167563,
    "price_change_24h": 0.0007987,
    "last_updated_at": "2024-07-05T23:12:41.775Z",
    "market_cap": 0,
    "market_cap_rank": null
  },
  "subsocial": {
    "cached_at": 1720221242123,
    "current_price": 0.00226779,
    "price_change_24h": -0.000029473735782372,
    "last_updated_at": "2024-07-05T23:13:23.409Z",
    "market_cap": 1917766,
    "market_cap_rank": 2248
  },
  "datahighway": {
    "cached_at": 1720221242123,
    "current_price": 0.03704823,
    "price_change_24h": -0.006485836197440823,
    "last_updated_at": "2024-07-05T23:13:43.209Z",
    "market_cap": 0,
    "market_cap_rank": null
  },
  "brz": {
    "cached_at": 1720221242123,
    "current_price": 0.182919,
    "price_change_24h": 0.00279373,
    "last_updated_at": "2024-07-05T23:13:54.143Z",
    "market_cap": 0,
    "market_cap_rank": null
  },
  "runes-x-bitcoin": {
    "cached_at": 1720221242123,
    "current_price": 0.00006458,
    "price_change_24h": 0.00000395,
    "last_updated_at": "2024-07-05T23:13:25.091Z",
    "market_cap": 0,
    "market_cap_rank": null
  },
  "wrapped-ehmnd": {
    "cached_at": 1720221242123,
    "current_price": 0.117371,
    "price_change_24h": -0.005889639854050999,
    "last_updated_at": "2024-07-05T23:11:20.814Z",
    "market_cap": 0,
    "market_cap_rank": null
  },
  "calamari-network": {
    "cached_at": 1720221242123,
    "current_price": 0.00054634,
    "price_change_24h": -0.000036321185785186,
    "last_updated_at": "2024-07-05T23:13:36.559Z",
    "market_cap": 2282344,
    "market_cap_rank": 2150
  },
  "mnet-continuum": {
    "cached_at": 1720221242123,
    "current_price": 0.02072325,
    "price_change_24h": -0.000461457408528768,
    "last_updated_at": "2024-07-05T23:13:45.213Z",
    "market_cap": 2739946,
    "market_cap_rank": 2048
  },
  "cirus": {
    "cached_at": 1720221242123,
    "current_price": 0.00699532,
    "price_change_24h": -0.001763887814956495,
    "last_updated_at": "2024-07-05T23:13:35.495Z",
    "market_cap": 934875,
    "market_cap_rank": 2730
  },
  "bitcoin-wizards": {
    "cached_at": 1720221242123,
    "current_price": 3.23,
    "price_change_24h": -0.06691707877329156,
    "last_updated_at": "2024-07-05T23:12:51.258Z",
    "market_cap": 67764654,
    "market_cap_rank": 483
  },
  "krest": {
    "cached_at": 1720221242123,
    "current_price": 0.139459,
    "price_change_24h": -0.004211319757186833,
    "last_updated_at": "2024-07-05T23:13:18.755Z",
    "market_cap": 0,
    "market_cap_rank": null
  },
  "panorama-swap-token": {
    "cached_at": 1717857182427,
    "current_price": null,
    "price_change_24h": null,
    "last_updated_at": null,
    "market_cap": null,
    "market_cap_rank": null
  },
  "jur": {
    "cached_at": 1717857182427,
    "current_price": 0.00135046,
    "price_change_24h": null,
    "last_updated_at": "2024-05-26T19:31:02.906Z",
    "market_cap": 355619,
    "market_cap_rank": 3395
  },
  "binance-peg-cardano": {
    "cached_at": 1720221242123,
    "current_price": 0.350412,
    "price_change_24h": -0.02625128306604929,
    "last_updated_at": "2024-07-05T23:12:35.800Z",
    "market_cap": 0,
    "market_cap_rank": null
  },
  "fusotao": {
    "cached_at": 1720221242123,
    "current_price": 0.0010308,
    "price_change_24h": 7.2167e-8,
    "last_updated_at": "2024-07-05T23:13:45.287Z",
    "market_cap": 0,
    "market_cap_rank": null
  },
  "acala": {
    "cached_at": 1720221242123,
    "current_price": 0.055953,
    "price_change_24h": -0.00398378249859558,
    "last_updated_at": "2024-07-05T23:13:41.719Z",
    "market_cap": 56999796,
    "market_cap_rank": 531
  },
  "boba-network": {
    "cached_at": 1720221242123,
    "current_price": 0.230611,
    "price_change_24h": 0.01291175,
    "last_updated_at": "2024-07-05T23:13:37.725Z",
    "market_cap": 88026534,
    "market_cap_rank": 404
  },
  "verse-bitcoin": {
    "cached_at": 1720221242123,
    "current_price": 0.00016461,
    "price_change_24h": -0.000008970175330106,
    "last_updated_at": "2024-07-05T23:13:42.250Z",
    "market_cap": 2110992,
    "market_cap_rank": 2188
  },
  "automata": {
    "cached_at": 1720221242123,
    "current_price": 0.083721,
    "price_change_24h": -0.005629962473650039,
    "last_updated_at": "2024-07-05T23:13:36.327Z",
    "market_cap": 42920348,
    "market_cap_rank": 626
  },
  "runecoin": {
    "cached_at": 1720221242123,
    "current_price": 0.00396418,
    "price_change_24h": -0.000182706788642259,
    "last_updated_at": "2024-07-05T23:13:16.820Z",
    "market_cap": 0,
    "market_cap_rank": null
  },
  "basilisk": {
    "cached_at": 1720221242123,
    "current_price": 0.00007759,
    "price_change_24h": 0.00000131,
    "last_updated_at": "2024-07-05T23:13:19.674Z",
    "market_cap": 1828963,
    "market_cap_rank": 2281
  },
  "centrifuge": {
    "cached_at": 1720221242123,
    "current_price": 0.403912,
    "price_change_24h": -0.025023391013209884,
    "last_updated_at": "2024-07-05T23:13:39.268Z",
    "market_cap": 200077005,
    "market_cap_rank": 242
  },
  "polkadex": {
    "cached_at": 1720221242123,
    "current_price": 0.250404,
    "price_change_24h": 0.02689006,
    "last_updated_at": "2024-07-05T23:13:43.548Z",
    "market_cap": 1867988,
    "market_cap_rank": 2267
  },
  "pha": {
    "cached_at": 1720221242123,
    "current_price": 0.123067,
    "price_change_24h": -0.006488638351687657,
    "last_updated_at": "2024-07-05T23:13:28.296Z",
    "market_cap": 90362692,
    "market_cap_rank": 394
  },
  "sirius-finance": {
    "cached_at": 1719181382264,
    "current_price": 0.00010714,
    "price_change_24h": -0.000002580559351624,
    "last_updated_at": "2024-06-23T22:13:58.416Z",
    "market_cap": 0,
    "market_cap_rank": null
  },
  "integritee": {
    "cached_at": 1720221242123,
    "current_price": 0.424708,
    "price_change_24h": 0.087299,
    "last_updated_at": "2024-07-05T23:13:19.706Z",
    "market_cap": 1688706,
    "market_cap_rank": 2343
  },
  "mantle": {
    "cached_at": 1720221242123,
    "current_price": 0.639476,
    "price_change_24h": -0.04630867611984035,
    "last_updated_at": "2024-07-05T23:13:17.630Z",
    "market_cap": 2088503437,
    "market_cap_rank": 41
  },
  "moonbeam": {
    "cached_at": 1720221242123,
    "current_price": 0.184893,
    "price_change_24h": -0.011004811400493695,
    "last_updated_at": "2024-07-05T23:13:17.097Z",
    "market_cap": 163222573,
    "market_cap_rank": 275
  },
  "compound-governance-token": {
    "cached_at": 1720221242123,
    "current_price": 47,
    "price_change_24h": 1.59,
    "last_updated_at": "2024-07-05T23:13:55.263Z",
    "market_cap": 321870860,
    "market_cap_rank": 167
  },
  "interbtc": {
    "cached_at": 1720221242123,
    "current_price": 58016,
    "price_change_24h": -1221.4391610313323,
    "last_updated_at": "2024-07-05T23:08:26.047Z",
    "market_cap": 0,
    "market_cap_rank": null
  },
  "altair": {
    "cached_at": 1720221242123,
    "current_price": 0.01357304,
    "price_change_24h": 0.00071429,
    "last_updated_at": "2024-07-05T23:13:17.716Z",
    "market_cap": 5349096,
    "market_cap_rank": 1639
  },
  "deeper-network": {
    "cached_at": 1720221242123,
    "current_price": 0.0029865,
    "price_change_24h": -0.000310197501859922,
    "last_updated_at": "2024-07-05T23:13:36.312Z",
    "market_cap": 0,
    "market_cap_rank": null
  },
  "nftmart-token": {
    "cached_at": 1720221242123,
    "current_price": 0.00415159,
    "price_change_24h": -0.000217301764726681,
    "last_updated_at": "2024-07-05T23:13:06.494Z",
    "market_cap": 0,
    "market_cap_rank": null
  },
  "commune-ai": {
    "cached_at": 1720221242123,
    "current_price": 0.289646,
    "price_change_24h": 0.0010502,
    "last_updated_at": "2024-07-05T23:13:23.529Z",
    "market_cap": 32507880,
    "market_cap_rank": 734
  },
  "citadel": {
    "cached_at": 1720221242123,
    "current_price": 0.00360202,
    "price_change_24h": -0.000004660010136158,
    "last_updated_at": "2024-07-05T23:12:40.153Z",
    "market_cap": 0,
    "market_cap_rank": null
  },
  "weth": {
    "cached_at": 1720221242123,
    "current_price": 2983.03,
    "price_change_24h": -137.72372068157847,
    "last_updated_at": "2024-07-05T23:13:39.955Z",
    "market_cap": 0,
    "market_cap_rank": null
  },
  "vara-network": {
    "cached_at": 1720221242123,
    "current_price": 0.03189225,
    "price_change_24h": -0.001098634368210325,
    "last_updated_at": "2024-07-05T23:13:26.979Z",
    "market_cap": 17247814,
    "market_cap_rank": 1007
  },
  "picasso": {
    "cached_at": 1720221242123,
    "current_price": 0.00127164,
    "price_change_24h": -0.000061046001990103,
    "last_updated_at": "2024-07-05T23:13:57.613Z",
    "market_cap": 7008359,
    "market_cap_rank": 1486
  },
  "moonwell": {
    "cached_at": 1720219682159,
    "current_price": 0.0010515,
    "price_change_24h": -0.000120374697859295,
    "last_updated_at": "2024-07-05T22:39:55.113Z",
    "market_cap": 577208,
    "market_cap_rank": 3026
  },
  "joystream": {
    "cached_at": 1720221242123,
    "current_price": 0.00845726,
    "price_change_24h": -0.000550238999007545,
    "last_updated_at": "2024-07-05T23:13:17.827Z",
    "market_cap": 7916607,
    "market_cap_rank": 1414
  },
  "pepe": {
    "cached_at": 1720221242123,
    "current_price": 0.00000895,
    "price_change_24h": -2.51095868406e-7,
    "last_updated_at": "2024-07-05T23:13:41.634Z",
    "market_cap": 3756491021,
    "market_cap_rank": 27
  },
  "sakura": {
    "cached_at": 1720221242123,
    "current_price": 0.00093221,
    "price_change_24h": 0.00016599,
    "last_updated_at": "2024-07-05T23:13:43.761Z",
    "market_cap": 148230,
    "market_cap_rank": 3786
  },
  "bitcoin": {
    "cached_at": 1720221242123,
    "current_price": 56727,
    "price_change_24h": -1333.241970187919,
    "last_updated_at": "2024-07-05T23:13:27.658Z",
    "market_cap": 1117592985340,
    "market_cap_rank": 1
  },
  "3dpass": {
    "cached_at": 1720221242123,
    "current_price": 0.00349079,
    "price_change_24h": -0.000021986710899993,
    "last_updated_at": "2024-07-05T23:12:42.475Z",
    "market_cap": 0,
    "market_cap_rank": null
  },
  "bifrost-voucher-manta": {
    "cached_at": 1720221242123,
    "current_price": 0.843041,
    "price_change_24h": -0.1837646860768697,
    "last_updated_at": "2024-07-05T23:09:00.700Z",
    "market_cap": 0,
    "market_cap_rank": null
  },
  "crowns": {
    "cached_at": 1720221242123,
    "current_price": 0.251873,
    "price_change_24h": -0.016062487375661298,
    "last_updated_at": "2024-07-05T23:13:32.422Z",
    "market_cap": 1463511,
    "market_cap_rank": 2444
  },
  "moonwell-artemis": {
    "cached_at": 1720221242123,
    "current_price": 0.02127002,
    "price_change_24h": -0.002241934775765488,
    "last_updated_at": "2024-07-05T23:13:35.163Z",
    "market_cap": 54326988,
    "market_cap_rank": 555
  },
  "aventus": {
    "cached_at": 1720221242123,
    "current_price": 1.99,
    "price_change_24h": -0.04195703809423601,
    "last_updated_at": "2024-07-05T23:13:51.273Z",
    "market_cap": 18435078,
    "market_cap_rank": 985
  },
  "clover-finance": {
    "cached_at": 1720221242123,
    "current_price": 0.04393435,
    "price_change_24h": -0.001946082238244808,
    "last_updated_at": "2024-07-05T23:14:01.125Z",
    "market_cap": 43901560,
    "market_cap_rank": 619
  },
  "billicat": {
    "cached_at": 1720221242123,
    "current_price": 0.00263363,
    "price_change_24h": -0.000167260583818819,
    "last_updated_at": "2024-07-05T23:12:50.978Z",
    "market_cap": 0,
    "market_cap_rank": null
  },
  "voucher-movr": {
    "cached_at": 1720136282415,
    "current_price": 12.19,
    "price_change_24h": -0.811641705263975,
    "last_updated_at": "2024-07-04T23:31:37.749Z",
    "market_cap": 0,
    "market_cap_rank": null
  },
  "acala-dollar-acala": {
    "cached_at": 1720216862874,
    "current_price": 5.22,
    "price_change_24h": 0.611688,
    "last_updated_at": "2024-07-05T21:59:23.283Z",
    "market_cap": 0,
    "market_cap_rank": null
  },
  "coinsbit-token": {
    "cached_at": 1720221242123,
    "current_price": 0.00011511,
    "price_change_24h": 0.00000237,
    "last_updated_at": "2024-07-05T23:11:52.400Z",
    "market_cap": 75890,
    "market_cap_rank": 4102
  },
  "stellar": {
    "cached_at": 1720221242123,
    "current_price": 0.085684,
    "price_change_24h": -0.003235214610952109,
    "last_updated_at": "2024-07-05T23:13:25.629Z",
    "market_cap": 2499179891,
    "market_cap_rank": 35
  },
  "enjincoin": {
    "cached_at": 1720221242123,
    "current_price": 0.164184,
    "price_change_24h": -0.000348038786596477,
    "last_updated_at": "2024-07-05T23:13:29.824Z",
    "market_cap": 266429028,
    "market_cap_rank": 190
  },
  "apecoin": {
    "cached_at": 1720221242123,
    "current_price": 0.706678,
    "price_change_24h": -0.08619104830502333,
    "last_updated_at": "2024-07-05T23:13:53.704Z",
    "market_cap": 442420395,
    "market_cap_rank": 141
  },
  "voucher-ksm": {
    "cached_at": 1720221242123,
    "current_price": 28.68,
    "price_change_24h": -1.0756192849717152,
    "last_updated_at": "2024-07-05T23:11:22.968Z",
    "market_cap": 0,
    "market_cap_rank": null
  },
  "matic-network": {
    "cached_at": 1720221242123,
    "current_price": 0.468364,
    "price_change_24h": -0.03761803025514082,
    "last_updated_at": "2024-07-05T23:13:39.023Z",
    "market_cap": 4345792647,
    "market_cap_rank": 24
  },
  "energy-web-token": {
    "cached_at": 1720221242123,
    "current_price": 2.02,
    "price_change_24h": -0.034230369016560847,
    "last_updated_at": "2024-07-05T23:13:34.415Z",
    "market_cap": 104534036,
    "market_cap_rank": 359
  },
  "bittensor": {
    "cached_at": 1720221242123,
    "current_price": 224.12,
    "price_change_24h": -2.9914378500808425,
    "last_updated_at": "2024-07-05T23:13:41.221Z",
    "market_cap": 1572420784,
    "market_cap_rank": 54
  },
  "staked-ether": {
    "cached_at": 1720221242123,
    "current_price": 2981.58,
    "price_change_24h": -137.32445588405199,
    "last_updated_at": "2024-07-05T23:13:40.262Z",
    "market_cap": 29066110166,
    "market_cap_rank": 7
  },
  "bouncebit-btc": {
    "cached_at": 1720221242123,
    "current_price": 56294,
    "price_change_24h": -1232.0407166241203,
    "last_updated_at": "2024-07-05T23:12:46.344Z",
    "market_cap": 0,
    "market_cap_rank": null
  },
  "rmrk": {
    "cached_at": 1720221242123,
    "current_price": 0.817738,
    "price_change_24h": -0.01688342786112196,
    "last_updated_at": "2024-07-05T23:13:36.629Z",
    "market_cap": 7786886,
    "market_cap_rank": 1417
  },
  "subsquid": {
    "cached_at": 1720221242123,
    "current_price": 0.110735,
    "price_change_24h": 0.0004784,
    "last_updated_at": "2024-07-05T23:13:39.683Z",
    "market_cap": 0,
    "market_cap_rank": null
  },
  "wrapped-fantom": {
    "cached_at": 1720221242123,
    "current_price": 0.428166,
    "price_change_24h": -0.027703683881674986,
    "last_updated_at": "2024-07-05T23:13:42.553Z",
    "market_cap": 0,
    "market_cap_rank": null
  },
  "equilibrium-token": {
    "cached_at": 1720221242123,
    "current_price": 0.00002876,
    "price_change_24h": 3.3161e-7,
    "last_updated_at": "2024-07-05T23:13:53.993Z",
    "market_cap": 0,
    "market_cap_rank": null
  },
  "neon": {
    "cached_at": 1720221242123,
    "current_price": 0.440647,
    "price_change_24h": -0.002816298768598513,
    "last_updated_at": "2024-07-05T23:13:34.839Z",
    "market_cap": 25417335,
    "market_cap_rank": 842
  },
  "aleph-zero": {
    "cached_at": 1720221242123,
    "current_price": 0.477842,
    "price_change_24h": -0.031200802454573406,
    "last_updated_at": "2024-07-05T23:13:37.213Z",
    "market_cap": 153383946,
    "market_cap_rank": 285
  },
  "bifrost-voucher-astr": {
    "cached_at": 1720221242123,
    "current_price": 0.067734,
    "price_change_24h": -0.000497949050816612,
    "last_updated_at": "2024-07-05T23:11:24.640Z",
    "market_cap": 0,
    "market_cap_rank": null
  },
  "polymesh": {
    "cached_at": 1720221242123,
    "current_price": 0.215586,
    "price_change_24h": -0.010941745838564276,
    "last_updated_at": "2024-07-05T23:13:39.918Z",
    "market_cap": 229849019,
    "market_cap_rank": 215
  },
  "first-digital-usd": {
    "cached_at": 1720221242123,
    "current_price": 1.001,
    "price_change_24h": 0.00416073,
    "last_updated_at": "2024-07-05T23:13:36.357Z",
    "market_cap": 1916349506,
    "market_cap_rank": 47
  },
  "venus-usdt": {
    "cached_at": 1720221242123,
    "current_price": 0.02402598,
    "price_change_24h": 0.0000959,
    "last_updated_at": "2024-07-05T23:10:48.722Z",
    "market_cap": 0,
    "market_cap_rank": null
  },
  "karura": {
    "cached_at": 1720221242123,
    "current_price": 0.076827,
    "price_change_24h": -0.002129823800786968,
    "last_updated_at": "2024-07-05T23:13:42.711Z",
    "market_cap": 8411142,
    "market_cap_rank": 1390
  },
  "kilt-protocol": {
    "cached_at": 1720221242123,
    "current_price": 0.189287,
    "price_change_24h": 0.0004872,
    "last_updated_at": "2024-07-05T23:13:59.321Z",
    "market_cap": 26136359,
    "market_cap_rank": 823
  },
  "stellaswap": {
    "cached_at": 1720221242123,
    "current_price": 0.01982742,
    "price_change_24h": -0.001167002656268925,
    "last_updated_at": "2024-07-05T23:07:29.104Z",
    "market_cap": 875801,
    "market_cap_rank": 2779
  },
  "frax": {
    "cached_at": 1720221242123,
    "current_price": 0.997616,
    "price_change_24h": 0.00017772,
    "last_updated_at": "2024-07-05T23:13:30.868Z",
    "market_cap": 647856110,
    "market_cap_rank": 104
  },
  "kusama": {
    "cached_at": 1720221242123,
    "current_price": 20.46,
    "price_change_24h": -0.7460213997171472,
    "last_updated_at": "2024-07-05T23:13:30.347Z",
    "market_cap": 310247026,
    "market_cap_rank": 170
  },
  "efinity": {
    "cached_at": 1720221242123,
    "current_price": 0.04371551,
    "price_change_24h": -0.006037851392789889,
    "last_updated_at": "2024-07-05T23:11:48.692Z",
    "market_cap": 3796251,
    "market_cap_rank": 1866
  },
  "solarbeam": {
    "cached_at": 1720221242123,
    "current_price": 0.00928127,
    "price_change_24h": -0.000915699159461259,
    "last_updated_at": "2024-07-05T23:04:58.050Z",
    "market_cap": 193079,
    "market_cap_rank": 3652
  },
  "crown-sovereign": {
    "cached_at": 1720221242123,
    "current_price": 0.00088042,
    "price_change_24h": -0.000134440536423768,
    "last_updated_at": "2024-07-05T23:12:51.026Z",
    "market_cap": 0,
    "market_cap_rank": null
  },
  "ausd-seed-karura": {
    "cached_at": 1720220702305,
    "current_price": 0.336352,
    "price_change_24h": -0.012342483097280756,
    "last_updated_at": "2024-07-05T22:58:20.637Z",
    "market_cap": 0,
    "market_cap_rank": null
  },
  "pancakeswap-token": {
    "cached_at": 1720221242123,
    "current_price": 1.74,
    "price_change_24h": -0.11457526457607448,
    "last_updated_at": "2024-07-05T23:13:22.898Z",
    "market_cap": 474943993,
    "market_cap_rank": 137
  },
  "dai": {
    "cached_at": 1720221242123,
    "current_price": 0.99904,
    "price_change_24h": -0.000570835480169896,
    "last_updated_at": "2024-07-05T23:10:50.990Z",
    "market_cap": 5204607914,
    "market_cap_rank": 21
  },
  "standard-protocol": {
    "cached_at": 1720221242123,
    "current_price": 0.02212455,
    "price_change_24h": -0.001014744290235105,
    "last_updated_at": "2024-07-05T23:13:34.465Z",
    "market_cap": 2012806,
    "market_cap_rank": 2220
  },
  "myria": {
    "cached_at": 1720221242123,
    "current_price": 0.00297192,
    "price_change_24h": -0.000044709569026357,
    "last_updated_at": "2024-07-05T23:13:37.863Z",
    "market_cap": 61156318,
    "market_cap_rank": 514
  },
  "binance-usd": {
    "cached_at": 1720221242123,
    "current_price": 0.987242,
    "price_change_24h": -0.003888455333692309,
    "last_updated_at": "2024-07-05T23:12:54.182Z",
    "market_cap": 68550748,
    "market_cap_rank": 487
  },
  "robonomics-network": {
    "cached_at": 1720221242123,
    "current_price": 3.12,
    "price_change_24h": -0.17264696202468155,
    "last_updated_at": "2024-07-05T23:13:16.626Z",
    "market_cap": 9000291,
    "market_cap_rank": 1349
  },
  "wrapped-bitcoin": {
    "cached_at": 1720221242123,
    "current_price": 56674,
    "price_change_24h": -1251.3704757537053,
    "last_updated_at": "2024-07-05T23:13:38.515Z",
    "market_cap": 8664160631,
    "market_cap_rank": 15
  },
  "edgeware": {
    "cached_at": 1720221242123,
    "current_price": 0.00010513,
    "price_change_24h": -0.000044926694203822,
    "last_updated_at": "2024-07-05T23:13:30.431Z",
    "market_cap": 730763,
    "market_cap_rank": 2878
  },
  "moonbeans": {
    "cached_at": 1720179542113,
    "current_price": 0.062018,
    "price_change_24h": -0.009289063047405233,
    "last_updated_at": "2024-07-05T11:27:31.616Z",
    "market_cap": 0,
    "market_cap_rank": null
  },
  "sats-ordinals": {
    "cached_at": 1720221242123,
    "current_price": 1.20069e-7,
    "price_change_24h": -2.8529261119e-8,
    "last_updated_at": "2024-07-05T23:13:40.631Z",
    "market_cap": 252409283,
    "market_cap_rank": 202
  },
  "arbitrum": {
    "cached_at": 1720221242123,
    "current_price": 0.624242,
    "price_change_24h": -0.0793241130955964,
    "last_updated_at": "2024-07-05T23:13:39.592Z",
    "market_cap": 2009973978,
    "market_cap_rank": 44
  },
  "syscoin": {
    "cached_at": 1720221242123,
    "current_price": 0.097231,
    "price_change_24h": -0.008531547385199206,
    "last_updated_at": "2024-07-05T23:13:36.894Z",
    "market_cap": 76384900,
    "market_cap_rank": 448
  },
  "beamswap": {
    "cached_at": 1720221242123,
    "current_price": 0.00035669,
    "price_change_24h": -0.000011681863215538,
    "last_updated_at": "2024-07-05T23:13:21.222Z",
    "market_cap": 630288,
    "market_cap_rank": 2972
  },
  "darwinia-network-native-token": {
    "cached_at": 1720221242123,
    "current_price": 0.00256623,
    "price_change_24h": -0.000246879985016335,
    "last_updated_at": "2024-07-05T23:13:30.707Z",
    "market_cap": 4229826,
    "market_cap_rank": 1776
  },
  "tinkernet": {
    "cached_at": 1718178182335,
    "current_price": null,
    "price_change_24h": null,
    "last_updated_at": null,
    "market_cap": null,
    "market_cap_rank": null
  },
  "5ire": {
    "cached_at": 1720221242123,
    "current_price": 0.02620958,
    "price_change_24h": -0.00416962157636985,
    "last_updated_at": "2024-07-05T23:13:54.425Z",
    "market_cap": 1143597,
    "market_cap_rank": 2601
  },
  "riverboat": {
    "cached_at": 1720185842151,
    "current_price": 24.25,
    "price_change_24h": -2.811766684760453,
    "last_updated_at": "2024-07-05T13:14:54.943Z",
    "market_cap": 24199,
    "market_cap_rank": 4422
  },
  "ajuna-network": {
    "cached_at": 1720221242123,
    "current_price": 0.069441,
    "price_change_24h": 0.00001033,
    "last_updated_at": "2024-07-05T23:13:55.442Z",
    "market_cap": 0,
    "market_cap_rank": null
  },
  "crust-network": {
    "cached_at": 1720221242123,
    "current_price": 0.571334,
    "price_change_24h": -0.05231172280940244,
    "last_updated_at": "2024-07-05T23:13:16.503Z",
    "market_cap": 17255394,
    "market_cap_rank": 1008
  },
  "stakestone-ether": {
    "cached_at": 1720221242123,
    "current_price": 3040.27,
    "price_change_24h": -148.2527713227596,
    "last_updated_at": "2024-07-05T23:13:43.593Z",
    "market_cap": 0,
    "market_cap_rank": null
  },
  "dock": {
    "cached_at": 1720221242123,
    "current_price": 0.00993205,
    "price_change_24h": -0.001801413191513598,
    "last_updated_at": "2024-07-05T23:13:09.295Z",
    "market_cap": 0,
    "market_cap_rank": null
  },
  "the-sandbox": {
    "cached_at": 1720221242123,
    "current_price": 0.279862,
    "price_change_24h": -0.007986810968170943,
    "last_updated_at": "2024-07-05T23:13:34.785Z",
    "market_cap": 638429140,
    "market_cap_rank": 105
  },
  "toshipad": {
    "cached_at": 1719806882697,
    "current_price": 0.02930362,
    "price_change_24h": null,
    "last_updated_at": "2024-06-26T18:32:29.596Z",
    "market_cap": 0,
    "market_cap_rank": null
  },
  "kava": {
    "cached_at": 1720221242123,
    "current_price": 0.362327,
    "price_change_24h": -0.01271384140291526,
    "last_updated_at": "2024-07-05T23:13:27.091Z",
    "market_cap": 392746220,
    "market_cap_rank": 155
  },
  "dora-factory": {
    "cached_at": 1720221242123,
    "current_price": 0.106924,
    "price_change_24h": -0.010460247350424848,
    "last_updated_at": "2024-07-05T23:13:07.856Z",
    "market_cap": 548943,
    "market_cap_rank": 3055
  },
  "kintsugi": {
    "cached_at": 1720221242123,
    "current_price": 0.619702,
    "price_change_24h": -0.006286854924906883,
    "last_updated_at": "2024-07-05T23:13:18.175Z",
    "market_cap": 1515291,
    "market_cap_rank": 2431
  },
  "ethereum-name-service": {
    "cached_at": 1720221242123,
    "current_price": 23.03,
    "price_change_24h": -0.2001012664076427,
    "last_updated_at": "2024-07-05T23:13:56.604Z",
    "market_cap": 729986012,
    "market_cap_rank": 95
  },
  "hydradx": {
    "cached_at": 1720221242123,
    "current_price": 0.00996467,
    "price_change_24h": -0.000037020371783918,
    "last_updated_at": "2024-07-05T23:13:19.447Z",
    "market_cap": 26407219,
    "market_cap_rank": 819
  },
  "wrapped-steth": {
    "cached_at": 1720221242123,
    "current_price": 3492.18,
    "price_change_24h": -168.07701301529005,
    "last_updated_at": "2024-07-05T23:13:31.598Z",
    "market_cap": 0,
    "market_cap_rank": null
  }
}